{
    "message": "",
    "total": 1,
    "items": [
        {
            "scr_selcode": "2832",
            "sub_id3": "IDSS3006",
            "sub_name": "社會創新黑客松",
            "scr_credit": 3.0,
            "scj_scr_mso": "選修",
            "scr_examid": "否",
            "scr_examfn": "否",
            "scr_exambf": "否",
            "cls_name": "社會創新學院綜合班",
            "scr_period": "(二)02-04 人702 江宜芳,黃慧慈,汪浩",
            "scr_precnt": 40.0,
            "scr_acptcnt": 23.0,
            "scr_remarks": null,
            "unt_ls": 3702,
            "cls_id": "SX02100",
            "sub_id": "20027",
            "scr_dup": "001",
            "scr_ldl": "課堂教學",
            "scr_english": "N",
            "scr_teacher": "江宜芳,黃慧慈,汪浩"
        }
    ]
}