{
    "d": {
        "message": "",
        "total": 123,
        "items": [
            {
                "scr_selcode": "0049",
                "sub_id3": "COB627",
                "sub_name": "全球商業趨勢",
                "scr_credit": 2.0,
                "scj_scr_mso": "選修",
                "scr_examid": "否",
                "scr_examfn": "否",
                "scr_exambf": "否",
                "cls_name": "商學院碩士綜合班",
                "scr_period": "(五)03-04 商804B 江向才",
                "scr_precnt": 30.0,
                "scr_acptcnt": 11.0,
                "scr_remarks": "學碩合班上課課程，需現場選課",
                "unt_ls": 4100,
                "cls_id": "CB00300",
                "sub_id": "13916",
                "scr_dup": "001"
            },
            {
                "scr_selcode": "0050",
                "sub_id3": "COB628",
                "sub_name": "智慧營運",
                "scr_credit": 2.0,
                "scj_scr_mso": "選修",
                "scr_examid": "否",
                "scr_examfn": "否",
                "scr_exambf": "否",
                "cls_name": "商學院碩士綜合班",
                "scr_period": "(二)09-10 圖212_資訊素養 仇介民,王婉倫",
                "scr_precnt": 30.0,
                "scr_acptcnt": 7.0,
                "scr_remarks": "學碩合班上課課程，需現場選課",
                "unt_ls": 4100,
                "cls_id": "CB00300",
                "sub_id": "48858",
                "scr_dup": "001"
            },
            {
                "scr_selcode": "0051",
                "sub_id3": "COB631",
                "sub_name": "創新成本與財務策略",
                "scr_credit": 2.0,
                "scj_scr_mso": "選修",
                "scr_examid": "否",
                "scr_examfn": "否",
                "scr_exambf": "否",
                "cls_name": "商學院碩士綜合班",
                "scr_period": "(五)07-08 商804B 邱安安,黃馨儀",
                "scr_precnt": 30.0,
                "scr_acptcnt": 7.0,
                "scr_remarks": "學碩合班上課課程",
                "unt_ls": 4100,
                "cls_id": "CB00300",
                "sub_id": "50171",
                "scr_dup": "001"
            },
            {
                "scr_selcode": "0052",
                "sub_id3": "COB630",
                "sub_name": "商業創新專題",
                "scr_credit": 4.0,
                "scj_scr_mso": "選修",
                "scr_examid": "否",
                "scr_examfn": "否",
                "scr_exambf": "否",
                "cls_name": "商學院碩士綜合班",
                "scr_period": "(一)01-04 商409 梁馨予,蔡勝男",
                "scr_precnt": 30.0,
                "scr_acptcnt": 19.0,
                "scr_remarks": "學碩合班上課課程",
                "unt_ls": 4100,
                "cls_id": "CB00300",
                "sub_id": "80571",
                "scr_dup": "001"
            },
            {
                "scr_selcode": "0130",
                "sub_id3": "ACCT671",
                "sub_name": "高等稅務會計",
                "scr_credit": 3.0,
                "scj_scr_mso": "必修",
                "scr_examid": "否",
                "scr_examfn": "否",
                "scr_exambf": "否",
                "cls_name": "會計碩一",
                "scr_period": "(一)06-08 商703 鄭竹君",
                "scr_precnt": 30.0,
                "scr_acptcnt": 27.0,
                "scr_remarks": " ",
                "unt_ls": 4101,
                "cls_id": "CB01310",
                "sub_id": "32901",
                "scr_dup": "001"
            },
            {
                "scr_selcode": "0131",
                "sub_id3": "ACCT641",
                "sub_name": "高等管理會計",
                "scr_credit": 3.0,
                "scj_scr_mso": "必修",
                "scr_examid": "否",
                "scr_examfn": "否",
                "scr_exambf": "否",
                "cls_name": "會計碩一",
                "scr_period": "(三)02-04 商1107 張森河",
                "scr_precnt": 30.0,
                "scr_acptcnt": 27.0,
                "scr_remarks": " ",
                "unt_ls": 4101,
                "cls_id": "CB01310",
                "sub_id": "78340",
                "scr_dup": "001"
            },
            {
                "scr_selcode": "0133",
                "sub_id3": "ACCT622",
                "sub_name": "財務會計專題研討",
                "scr_credit": 3.0,
                "scj_scr_mso": "選修",
                "scr_examid": "否",
                "scr_examfn": "否",
                "scr_exambf": "否",
                "cls_name": "會計碩一",
                "scr_period": "(二)02-04 商1107 施念恕",
                "scr_precnt": 30.0,
                "scr_acptcnt": 19.0,
                "scr_remarks": "於註冊選課日後方開放外所選課",
                "unt_ls": 4101,
                "cls_id": "CB01310",
                "sub_id": "38181",
                "scr_dup": "001"
            },
            {
                "scr_selcode": "0134",
                "sub_id3": "ACCT628",
                "sub_name": "國際會計研討",
                "scr_credit": 3.0,
                "scj_scr_mso": "選修",
                "scr_examid": "否",
                "scr_examfn": "否",
                "scr_exambf": "否",
                "cls_name": "會計碩一",
                "scr_period": "(二)07-09 商1109 康淑珍",
                "scr_precnt": 30.0,
                "scr_acptcnt": 11.0,
                "scr_remarks": "於註冊選課日後方開放外所選課",
                "unt_ls": 4101,
                "cls_id": "CB01310",
                "sub_id": "42751",
                "scr_dup": "001"
            },
            {
                "scr_selcode": "0135",
                "sub_id3": "COB601",
                "sub_name": "碩士論文",
                "scr_credit": 0.0,
                "scj_scr_mso": "必修",
                "scr_examid": "否",
                "scr_examfn": "否",
                "scr_exambf": "否",
                "cls_name": "會計碩二",
                "scr_period": "(日)01-02 未排教室 黃馨儀",
                "scr_precnt": 30.0,
                "scr_acptcnt": 23.0,
                "scr_remarks": " ",
                "unt_ls": 4101,
                "cls_id": "CB01320",
                "sub_id": "61530",
                "scr_dup": "001"
            },
            {
                "scr_selcode": "0136",
                "sub_id3": "PF653",
                "sub_name": "企業租稅策略",
                "scr_credit": 3.0,
                "scj_scr_mso": "選修",
                "scr_examid": "否",
                "scr_examfn": "否",
                "scr_exambf": "否",
                "cls_name": "會計碩二",
                "scr_period": "(三)07-09 商808A 蕭子誼",
                "scr_precnt": 30.0,
                "scr_acptcnt": 26.0,
                "scr_remarks": "於註冊選課日後方開放外所選課",
                "unt_ls": 4101,
                "cls_id": "CB01320",
                "sub_id": "15922",
                "scr_dup": "001"
            },
            {
                "scr_selcode": "0139",
                "sub_id3": "ACCT663",
                "sub_name": "審計專題研討",
                "scr_credit": 3.0,
                "scj_scr_mso": "選修",
                "scr_examid": "否",
                "scr_examfn": "否",
                "scr_exambf": "否",
                "cls_name": "會計碩二",
                "scr_period": "(四)02-04 商1107 紀信義",
                "scr_precnt": 30.0,
                "scr_acptcnt": 21.0,
                "scr_remarks": "於註冊選課日後方開放外所選課",
                "unt_ls": 4101,
                "cls_id": "CB01320",
                "sub_id": "67853",
                "scr_dup": "001"
            },
            {
                "scr_selcode": "3843",
                "sub_id3": "ACCT692",
                "sub_name": "人工智慧與會計專題研討",
                "scr_credit": 3.0,
                "scj_scr_mso": "選修",
                "scr_examid": "否",
                "scr_examfn": "否",
                "scr_exambf": "否",
                "cls_name": "會計碩二",
                "scr_period": "(四)07-09 商1107 高惠松",
                "scr_precnt": 30.0,
                "scr_acptcnt": 12.0,
                "scr_remarks": null,
                "unt_ls": 4101,
                "cls_id": "CB01320",
                "sub_id": "99888",
                "scr_dup": "001"
            },
            {
                "scr_selcode": "2194",
                "sub_id3": "MGT620",
                "sub_name": "行銷管理",
                "scr_credit": 3.0,
                "scj_scr_mso": "必修",
                "scr_examid": "否",
                "scr_examfn": "否",
                "scr_exambf": "否",
                "cls_name": "企管碩一",
                "scr_period": "(二)06-08 商701 王智弘",
                "scr_precnt": 20.0,
                "scr_acptcnt": 19.0,
                "scr_remarks": " ",
                "unt_ls": 4102,
                "cls_id": "CM01310",
                "sub_id": "14740",
                "scr_dup": "001"
            },
            {
                "scr_selcode": "2195",
                "sub_id3": "MGT651",
                "sub_name": "作業管理",
                "scr_credit": 3.0,
                "scj_scr_mso": "必修",
                "scr_examid": "否",
                "scr_examfn": "否",
                "scr_exambf": "否",
                "cls_name": "企管碩一",
                "scr_period": "(一)06-08 商503 黃誠甫",
                "scr_precnt": 20.0,
                "scr_acptcnt": 21.0,
                "scr_remarks": " ",
                "unt_ls": 4102,
                "cls_id": "CM01310",
                "sub_id": "19710",
                "scr_dup": "001"
            },
            {
                "scr_selcode": "2196",
                "sub_id3": "FINA630",
                "sub_name": "財務管理",
                "scr_credit": 3.0,
                "scj_scr_mso": "必修",
                "scr_examid": "否",
                "scr_examfn": "否",
                "scr_exambf": "否",
                "cls_name": "企管碩一",
                "scr_period": "(二)02-04 商701 黃禮林",
                "scr_precnt": 20.0,
                "scr_acptcnt": 19.0,
                "scr_remarks": " ",
                "unt_ls": 4102,
                "cls_id": "CM01310",
                "sub_id": "37750",
                "scr_dup": "001"
            },
            {
                "scr_selcode": "2198",
                "sub_id3": "STAT629",
                "sub_name": "數量方法",
                "scr_credit": 3.0,
                "scj_scr_mso": "選修",
                "scr_examid": "否",
                "scr_examfn": "否",
                "scr_exambf": "否",
                "cls_name": "企管碩一",
                "scr_period": "(四)07-09 商503 陳建文",
                "scr_precnt": 20.0,
                "scr_acptcnt": 18.0,
                "scr_remarks": " ",
                "unt_ls": 4102,
                "cls_id": "CM01310",
                "sub_id": "62550",
                "scr_dup": "001"
            },
            {
                "scr_selcode": "2199",
                "sub_id3": "MGT697",
                "sub_name": "碩士論文",
                "scr_credit": 0.0,
                "scj_scr_mso": "必修",
                "scr_examid": "否",
                "scr_examfn": "否",
                "scr_exambf": "否",
                "cls_name": "企管碩二",
                "scr_period": " ",
                "scr_precnt": 0.0,
                "scr_acptcnt": 18.0,
                "scr_remarks": " ",
                "unt_ls": 4102,
                "cls_id": "CM01320",
                "sub_id": "61530",
                "scr_dup": "001"
            },
            {
                "scr_selcode": "2200",
                "sub_id3": "MGT656",
                "sub_name": "企業專業實習(一)",
                "scr_credit": 3.0,
                "scj_scr_mso": "選修",
                "scr_examid": "否",
                "scr_examfn": "否",
                "scr_exambf": "否",
                "cls_name": "企管碩二",
                "scr_period": "(六)11     未排教室 張秀樺,黃禮林",
                "scr_precnt": 60.0,
                "scr_acptcnt": 1.0,
                "scr_remarks": "不開放網路加退選。",
                "unt_ls": 4102,
                "cls_id": "CM01320",
                "sub_id": "13002",
                "scr_dup": "001"
            },
            {
                "scr_selcode": "2202",
                "sub_id3": "ITRA669",
                "sub_name": "服務業行銷",
                "scr_credit": 3.0,
                "scj_scr_mso": "選修",
                "scr_examid": "否",
                "scr_examfn": "否",
                "scr_exambf": "否",
                "cls_name": "企管碩二",
                "scr_period": "(五)07-09 商503 佘日新",
                "scr_precnt": 20.0,
                "scr_acptcnt": 17.0,
                "scr_remarks": " ",
                "unt_ls": 4102,
                "cls_id": "CM01320",
                "sub_id": "18341",
                "scr_dup": "001"
            },
            {
                "scr_selcode": "2203",
                "sub_id3": "ITRA621",
                "sub_name": "網路行銷",
                "scr_credit": 3.0,
                "scj_scr_mso": "選修",
                "scr_examid": "否",
                "scr_examfn": "否",
                "scr_exambf": "否",
                "cls_name": "企管碩二",
                "scr_period": "(五)02-04 商501 陳建文",
                "scr_precnt": 20.0,
                "scr_acptcnt": 5.0,
                "scr_remarks": " ",
                "unt_ls": 4102,
                "cls_id": "CM01320",
                "sub_id": "63811",
                "scr_dup": "001"
            },
            {
                "scr_selcode": "0212",
                "sub_id3": "ITRA639",
                "sub_name": "國際貿易經營管理專題(二)",
                "scr_credit": 1.0,
                "scj_scr_mso": "必修",
                "scr_examid": "否",
                "scr_examfn": "否",
                "scr_exambf": "否",
                "cls_name": "國貿碩一",
                "scr_period": "(二)05-06 商702 韓宜",
                "scr_precnt": 40.0,
                "scr_acptcnt": 21.0,
                "scr_remarks": " ",
                "unt_ls": 4103,
                "cls_id": "CB02310",
                "sub_id": "41515",
                "scr_dup": "001"
            },
            {
                "scr_selcode": "0213",
                "sub_id3": "ITRA665",
                "sub_name": "國際企業管理",
                "scr_credit": 3.0,
                "scj_scr_mso": "必修",
                "scr_examid": "否",
                "scr_examfn": "否",
                "scr_exambf": "否",
                "cls_name": "國貿碩一",
                "scr_period": "(三)02-04 商702 韓宜",
                "scr_precnt": 40.0,
                "scr_acptcnt": 24.0,
                "scr_remarks": " ",
                "unt_ls": 4103,
                "cls_id": "CB02310",
                "sub_id": "41870",
                "scr_dup": "001"
            },
            {
                "scr_selcode": "0214",
                "sub_id3": "ITRA659",
                "sub_name": "全球行銷管理專題",
                "scr_credit": 3.0,
                "scj_scr_mso": "選修",
                "scr_examid": "否",
                "scr_examfn": "否",
                "scr_exambf": "否",
                "cls_name": "國貿碩一",
                "scr_period": "(二)02-04 商702 曾鼎翔,林呈昱",
                "scr_precnt": 40.0,
                "scr_acptcnt": 15.0,
                "scr_remarks": null,
                "unt_ls": 4103,
                "cls_id": "CB02310",
                "sub_id": "13903",
                "scr_dup": "001"
            },
            {
                "scr_selcode": "0215",
                "sub_id3": "ITRA634",
                "sub_name": "全球財務管理專題",
                "scr_credit": 3.0,
                "scj_scr_mso": "選修",
                "scr_examid": "否",
                "scr_examfn": "否",
                "scr_exambf": "否",
                "cls_name": "國貿碩一",
                "scr_period": "(三)07-09 商704 吳文臨,莊逸偉",
                "scr_precnt": 40.0,
                "scr_acptcnt": 5.0,
                "scr_remarks": null,
                "unt_ls": 4103,
                "cls_id": "CB02310",
                "sub_id": "13904",
                "scr_dup": "001"
            },
            {
                "scr_selcode": "0216",
                "sub_id3": "ITRA623",
                "sub_name": "全球運籌管理專題",
                "scr_credit": 3.0,
                "scj_scr_mso": "選修",
                "scr_examid": "否",
                "scr_examfn": "否",
                "scr_exambf": "否",
                "cls_name": "國貿碩一",
                "scr_period": "(四)02-04 商702 蔡耀德",
                "scr_precnt": 40.0,
                "scr_acptcnt": 15.0,
                "scr_remarks": null,
                "unt_ls": 4103,
                "cls_id": "CB02310",
                "sub_id": "13905",
                "scr_dup": "001"
            },
            {
                "scr_selcode": "0218",
                "sub_id3": "ITRA629",
                "sub_name": "跨境電子商務專題",
                "scr_credit": 3.0,
                "scj_scr_mso": "選修",
                "scr_examid": "否",
                "scr_examfn": "否",
                "scr_exambf": "否",
                "cls_name": "國貿碩一",
                "scr_period": "(一)07-09 商702 江成欣",
                "scr_precnt": 40.0,
                "scr_acptcnt": 9.0,
                "scr_remarks": null,
                "unt_ls": 4103,
                "cls_id": "CB02310",
                "sub_id": "51991",
                "scr_dup": "001"
            },
            {
                "scr_selcode": "0219",
                "sub_id3": "COB601",
                "sub_name": "碩士論文",
                "scr_credit": 0.0,
                "scj_scr_mso": "必修",
                "scr_examid": "否",
                "scr_examfn": "否",
                "scr_exambf": "否",
                "cls_name": "國貿碩二",
                "scr_period": " ",
                "scr_precnt": 0.0,
                "scr_acptcnt": 24.0,
                "scr_remarks": " ",
                "unt_ls": 4103,
                "cls_id": "CB02320",
                "sub_id": "61530",
                "scr_dup": "001"
            },
            {
                "scr_selcode": "0220",
                "sub_id3": "ITRA451",
                "sub_name": "國際貿易經營管理田野研究",
                "scr_credit": 3.0,
                "scj_scr_mso": "選修",
                "scr_examid": "否",
                "scr_examfn": "否",
                "scr_exambf": "否",
                "cls_name": "國貿碩二",
                "scr_period": "(日)11-13 未排教室 吳廣文",
                "scr_precnt": 60.0,
                "scr_acptcnt": 16.0,
                "scr_remarks": "限參與移地教學國貿系同學選修",
                "unt_ls": 4103,
                "cls_id": "CB02320",
                "sub_id": "41408",
                "scr_dup": "001"
            },
            {
                "scr_selcode": "0221",
                "sub_id3": "ITRA780",
                "sub_name": "專業實習",
                "scr_credit": 3.0,
                "scj_scr_mso": "選修",
                "scr_examid": "否",
                "scr_examfn": "否",
                "scr_exambf": "否",
                "cls_name": "國貿碩二",
                "scr_period": "(日)06-08 未排教室 林呈昱",
                "scr_precnt": 60.0,
                "scr_acptcnt": 1.0,
                "scr_remarks": "限有錄取通知之國貿碩班同學加選",
                "unt_ls": 4103,
                "cls_id": "CB02320",
                "sub_id": "43035",
                "scr_dup": "001"
            },
            {
                "scr_selcode": "0222",
                "sub_id3": "ITRA678",
                "sub_name": "區域經貿專題",
                "scr_credit": 3.0,
                "scj_scr_mso": "選修",
                "scr_examid": "否",
                "scr_examfn": "否",
                "scr_exambf": "否",
                "cls_name": "國貿碩二",
                "scr_period": "(四)11-13 商701 林俊宏",
                "scr_precnt": 30.0,
                "scr_acptcnt": 8.0,
                "scr_remarks": null,
                "unt_ls": 4103,
                "cls_id": "CB02320",
                "sub_id": "43541",
                "scr_dup": "001"
            },
            {
                "scr_selcode": "0223",
                "sub_id3": "ITRA670",
                "sub_name": "創業與創新專題",
                "scr_credit": 3.0,
                "scj_scr_mso": "選修",
                "scr_examid": "否",
                "scr_examfn": "否",
                "scr_exambf": "否",
                "cls_name": "國貿碩二",
                "scr_period": "(三)02-04 商701 董正玫",
                "scr_precnt": 30.0,
                "scr_acptcnt": 17.0,
                "scr_remarks": "限國貿系同學選修。",
                "unt_ls": 4103,
                "cls_id": "CB02320",
                "sub_id": "51340",
                "scr_dup": "001"
            },
            {
                "scr_selcode": "0428",
                "sub_id3": "PF601",
                "sub_name": "公共支出理論",
                "scr_credit": 3.0,
                "scj_scr_mso": "必修",
                "scr_examid": "否",
                "scr_examfn": "否",
                "scr_exambf": "否",
                "cls_name": "財稅碩一",
                "scr_period": "(二)02-04 商1111 游慧光",
                "scr_precnt": 20.0,
                "scr_acptcnt": 11.0,
                "scr_remarks": " ",
                "unt_ls": 4104,
                "cls_id": "CB05310",
                "sub_id": "06610",
                "scr_dup": "001"
            },
            {
                "scr_selcode": "0429",
                "sub_id3": "COB602",
                "sub_name": "研究方法",
                "scr_credit": 3.0,
                "scj_scr_mso": "必修",
                "scr_examid": "否",
                "scr_examfn": "否",
                "scr_exambf": "否",
                "cls_name": "財稅碩一",
                "scr_period": "(一)07-09 商1111 梁景洋",
                "scr_precnt": 20.0,
                "scr_acptcnt": 12.0,
                "scr_remarks": " ",
                "unt_ls": 4104,
                "cls_id": "CB05310",
                "sub_id": "26210",
                "scr_dup": "001"
            },
            {
                "scr_selcode": "0430",
                "sub_id3": "PF640",
                "sub_name": "租稅理論",
                "scr_credit": 3.0,
                "scj_scr_mso": "必修",
                "scr_examid": "否",
                "scr_examfn": "否",
                "scr_exambf": "否",
                "cls_name": "財稅碩一",
                "scr_period": "(四)02-04 商1111 黃瓊如,梁景洋",
                "scr_precnt": 20.0,
                "scr_acptcnt": 11.0,
                "scr_remarks": " ",
                "unt_ls": 4104,
                "cls_id": "CB05310",
                "sub_id": "37040",
                "scr_dup": "001"
            },
            {
                "scr_selcode": "0431",
                "sub_id3": "PF610",
                "sub_name": "地方財政",
                "scr_credit": 3.0,
                "scj_scr_mso": "選修",
                "scr_examid": "否",
                "scr_examfn": "否",
                "scr_exambf": "否",
                "cls_name": "財稅碩一",
                "scr_period": "(四)07-09 商1111 何艷宏",
                "scr_precnt": 20.0,
                "scr_acptcnt": 10.0,
                "scr_remarks": null,
                "unt_ls": 4104,
                "cls_id": "CB05310",
                "sub_id": "17650",
                "scr_dup": "001"
            },
            {
                "scr_selcode": "0432",
                "sub_id3": "PF666",
                "sub_name": "國際商用英文溝通(二)",
                "scr_credit": 3.0,
                "scj_scr_mso": "選修",
                "scr_examid": "否",
                "scr_examfn": "否",
                "scr_exambf": "否",
                "cls_name": "財稅碩一",
                "scr_period": "(三)02-04 商1111 游慧光",
                "scr_precnt": 20.0,
                "scr_acptcnt": 10.0,
                "scr_remarks": null,
                "unt_ls": 4104,
                "cls_id": "CB05310",
                "sub_id": "41887",
                "scr_dup": "001"
            },
            {
                "scr_selcode": "0433",
                "sub_id3": "COB601",
                "sub_name": "碩士論文",
                "scr_credit": 0.0,
                "scj_scr_mso": "必修",
                "scr_examid": "否",
                "scr_examfn": "否",
                "scr_exambf": "否",
                "cls_name": "財稅碩二",
                "scr_period": "(六)00     未排教室",
                "scr_precnt": 0.0,
                "scr_acptcnt": 15.0,
                "scr_remarks": " ",
                "unt_ls": 4104,
                "cls_id": "CB05320",
                "sub_id": "61530",
                "scr_dup": "001"
            },
            {
                "scr_selcode": "0434",
                "sub_id3": "PF615",
                "sub_name": "社會安全制度",
                "scr_credit": 3.0,
                "scj_scr_mso": "選修",
                "scr_examid": "否",
                "scr_examfn": "否",
                "scr_exambf": "否",
                "cls_name": "財稅碩二",
                "scr_period": "(一)02-04 商1111 梁景洋",
                "scr_precnt": 20.0,
                "scr_acptcnt": 14.0,
                "scr_remarks": null,
                "unt_ls": 4104,
                "cls_id": "CB05320",
                "sub_id": "20034",
                "scr_dup": "001"
            },
            {
                "scr_selcode": "0435",
                "sub_id3": "PF630",
                "sub_name": "財政金融政策",
                "scr_credit": 3.0,
                "scj_scr_mso": "選修",
                "scr_examid": "否",
                "scr_examfn": "否",
                "scr_exambf": "否",
                "cls_name": "財稅碩二",
                "scr_period": "(三)07-09 商1111 楊建成,吳朝欽",
                "scr_precnt": 20.0,
                "scr_acptcnt": 9.0,
                "scr_remarks": " ",
                "unt_ls": 4104,
                "cls_id": "CB05320",
                "sub_id": "37650",
                "scr_dup": "001"
            },
            {
                "scr_selcode": "0436",
                "sub_id3": "PF652",
                "sub_name": "國際租稅",
                "scr_credit": 3.0,
                "scj_scr_mso": "選修",
                "scr_examid": "否",
                "scr_examfn": "否",
                "scr_exambf": "否",
                "cls_name": "財稅碩二",
                "scr_period": "(一)07-09 商1113 謝耀智",
                "scr_precnt": 7.0,
                "scr_acptcnt": 6.0,
                "scr_remarks": null,
                "unt_ls": 4104,
                "cls_id": "CB05320",
                "sub_id": "41640",
                "scr_dup": "001"
            },
            {
                "scr_selcode": "0524",
                "sub_id3": "STAT692",
                "sub_name": "專題討論(二)",
                "scr_credit": 1.0,
                "scj_scr_mso": "必修",
                "scr_examid": "否",
                "scr_examfn": "否",
                "scr_exambf": "否",
                "cls_name": "統精碩一",
                "scr_period": "(五)07     商1011 王价輝",
                "scr_precnt": 30.0,
                "scr_acptcnt": 17.0,
                "scr_remarks": " ",
                "unt_ls": 4105,
                "cls_id": "CB07310",
                "sub_id": "43140",
                "scr_dup": "001"
            },
            {
                "scr_selcode": "0525",
                "sub_id3": "STAT619",
                "sub_name": "R程式設計與統計分析",
                "scr_credit": 3.0,
                "scj_scr_mso": "選修",
                "scr_examid": "否",
                "scr_examfn": "否",
                "scr_exambf": "否",
                "cls_name": "統精碩一",
                "scr_period": "(二)07-09 商702 鍾冬川",
                "scr_precnt": 30.0,
                "scr_acptcnt": 21.0,
                "scr_remarks": null,
                "unt_ls": 4105,
                "cls_id": "CB07310",
                "sub_id": "04327",
                "scr_dup": "001"
            },
            {
                "scr_selcode": "0526",
                "sub_id3": "STAT656",
                "sub_name": "可信度理論",
                "scr_credit": 3.0,
                "scj_scr_mso": "選修",
                "scr_examid": "否",
                "scr_examfn": "否",
                "scr_exambf": "否",
                "cls_name": "統精碩一",
                "scr_period": "(三)07-09 商1013 王价輝",
                "scr_precnt": 20.0,
                "scr_acptcnt": 7.0,
                "scr_remarks": null,
                "unt_ls": 4105,
                "cls_id": "CB07310",
                "sub_id": "12931",
                "scr_dup": "001"
            },
            {
                "scr_selcode": "0527",
                "sub_id3": "FINA620",
                "sub_name": "衍生性金融商品",
                "scr_credit": 3.0,
                "scj_scr_mso": "選修",
                "scr_examid": "否",
                "scr_examfn": "否",
                "scr_exambf": "否",
                "cls_name": "統精碩一",
                "scr_period": "(四)07-09 商1011 林問一",
                "scr_precnt": 30.0,
                "scr_acptcnt": 16.0,
                "scr_remarks": null,
                "unt_ls": 4105,
                "cls_id": "CB07310",
                "sub_id": "30380",
                "scr_dup": "001"
            },
            {
                "scr_selcode": "0528",
                "sub_id3": "STAT613",
                "sub_name": "統計計算",
                "scr_credit": 3.0,
                "scj_scr_mso": "選修",
                "scr_examid": "否",
                "scr_examfn": "否",
                "scr_exambf": "否",
                "cls_name": "統精碩一",
                "scr_period": "(二)02-04 資電B14(電腦實習室) 陳婉淑",
                "scr_precnt": 30.0,
                "scr_acptcnt": 9.0,
                "scr_remarks": null,
                "unt_ls": 4105,
                "cls_id": "CB07310",
                "sub_id": "46280",
                "scr_dup": "001"
            },
            {
                "scr_selcode": "0529",
                "sub_id3": "STAT653",
                "sub_name": "高等精算數學",
                "scr_credit": 3.0,
                "scj_scr_mso": "選修",
                "scr_examid": "否",
                "scr_examfn": "否",
                "scr_exambf": "否",
                "cls_name": "統精碩一",
                "scr_period": "(一)06-08 商1011 林麗芬",
                "scr_precnt": 30.0,
                "scr_acptcnt": 8.0,
                "scr_remarks": null,
                "unt_ls": 4105,
                "cls_id": "CB07310",
                "sub_id": "77920",
                "scr_dup": "001"
            },
            {
                "scr_selcode": "0530",
                "sub_id3": "STAT632",
                "sub_name": "高等數理統計學(二)",
                "scr_credit": 3.0,
                "scj_scr_mso": "選修",
                "scr_examid": "否",
                "scr_examfn": "否",
                "scr_exambf": "否",
                "cls_name": "統精碩一",
                "scr_period": "(四)02-04 商1011 王婉倫",
                "scr_precnt": 30.0,
                "scr_acptcnt": 16.0,
                "scr_remarks": null,
                "unt_ls": 4105,
                "cls_id": "CB07310",
                "sub_id": "78070",
                "scr_dup": "001"
            },
            {
                "scr_selcode": "0531",
                "sub_id3": "COB601",
                "sub_name": "碩士論文",
                "scr_credit": 0.0,
                "scj_scr_mso": "必修",
                "scr_examid": "否",
                "scr_examfn": "否",
                "scr_exambf": "否",
                "cls_name": "統精碩二",
                "scr_period": "   00     未排教室 陳婉淑,李仁佑,李燊銘,林麗芬,劉峰旗,張育瑋,鍾冬川",
                "scr_precnt": 40.0,
                "scr_acptcnt": 27.0,
                "scr_remarks": " ",
                "unt_ls": 4105,
                "cls_id": "CB07320",
                "sub_id": "61530",
                "scr_dup": "001"
            },
            {
                "scr_selcode": "0532",
                "sub_id3": "STAT655",
                "sub_name": "退休金數學",
                "scr_credit": 3.0,
                "scj_scr_mso": "選修",
                "scr_examid": "否",
                "scr_examfn": "否",
                "scr_exambf": "否",
                "cls_name": "統精碩二",
                "scr_period": "(二)06-08 商1013 林麗芬",
                "scr_precnt": 20.0,
                "scr_acptcnt": 10.0,
                "scr_remarks": null,
                "unt_ls": 4105,
                "cls_id": "CB07320",
                "sub_id": "38750",
                "scr_dup": "001"
            },
            {
                "scr_selcode": "0533",
                "sub_id3": "STAT674",
                "sub_name": "產險精算實務(二)",
                "scr_credit": 2.0,
                "scj_scr_mso": "選修",
                "scr_examid": "否",
                "scr_examfn": "否",
                "scr_exambf": "否",
                "cls_name": "統精碩二",
                "scr_period": "(六)01-02 商1013 周弘毅,簡仲明,陳貴霞,曾慶泓",
                "scr_precnt": 20.0,
                "scr_acptcnt": 13.0,
                "scr_remarks": "限統計系統精碩班學生。",
                "unt_ls": 4105,
                "cls_id": "CB07320",
                "sub_id": "41190",
                "scr_dup": "001"
            },
            {
                "scr_selcode": "0535",
                "sub_id3": "STAT672",
                "sub_name": "壽險精算實務(二)",
                "scr_credit": 2.0,
                "scj_scr_mso": "選修",
                "scr_examid": "否",
                "scr_examfn": "否",
                "scr_exambf": "否",
                "cls_name": "統精碩二",
                "scr_period": "(六)03-04 商1013 朱立明,劉人楷,文子豐,葉爾康",
                "scr_precnt": 20.0,
                "scr_acptcnt": 14.0,
                "scr_remarks": "限統計系統精碩班學生。",
                "unt_ls": 4105,
                "cls_id": "CB07320",
                "sub_id": "65940",
                "scr_dup": "001"
            },
            {
                "scr_selcode": "0536",
                "sub_id3": "STAT614",
                "sub_name": "類別資料分析",
                "scr_credit": 3.0,
                "scj_scr_mso": "選修",
                "scr_examid": "否",
                "scr_examfn": "否",
                "scr_exambf": "否",
                "cls_name": "統精碩二",
                "scr_period": "(五)02-04 商1011 林宗儀",
                "scr_precnt": 30.0,
                "scr_acptcnt": 7.0,
                "scr_remarks": null,
                "unt_ls": 4105,
                "cls_id": "CB07320",
                "sub_id": "69250",
                "scr_dup": "001"
            },
            {
                "scr_selcode": "0587",
                "sub_id3": "ECON631",
                "sub_name": "計量經濟學(一)",
                "scr_credit": 3.0,
                "scj_scr_mso": "必修",
                "scr_examid": "否",
                "scr_examfn": "否",
                "scr_exambf": "否",
                "cls_name": "經濟碩一",
                "scr_period": "(三)07-09 商911 郭祐誠",
                "scr_precnt": 30.0,
                "scr_acptcnt": 12.0,
                "scr_remarks": " ",
                "unt_ls": 4106,
                "cls_id": "CB08310",
                "sub_id": "28310",
                "scr_dup": "001"
            },
            {
                "scr_selcode": "0588",
                "sub_id3": "ECON787",
                "sub_name": "專題討論(二)",
                "scr_credit": 1.0,
                "scj_scr_mso": "必修",
                "scr_examid": "否",
                "scr_examfn": "否",
                "scr_exambf": "否",
                "cls_name": "經濟碩一",
                "scr_period": "(四)07     商907 林雅淇",
                "scr_precnt": 30.0,
                "scr_acptcnt": 6.0,
                "scr_remarks": " ",
                "unt_ls": 4106,
                "cls_id": "CB08310",
                "sub_id": "43140",
                "scr_dup": "001"
            },
            {
                "scr_selcode": "0589",
                "sub_id3": "ECON611",
                "sub_name": "總體經濟理論(一)",
                "scr_credit": 3.0,
                "scj_scr_mso": "必修",
                "scr_examid": "否",
                "scr_examfn": "否",
                "scr_exambf": "否",
                "cls_name": "經濟碩一",
                "scr_period": "(五)02-04 商907 秦國軒",
                "scr_precnt": 30.0,
                "scr_acptcnt": 10.0,
                "scr_remarks": " ",
                "unt_ls": 4106,
                "cls_id": "CB08310",
                "sub_id": "74141",
                "scr_dup": "001"
            },
            {
                "scr_selcode": "0590",
                "sub_id3": "COB601",
                "sub_name": "碩士論文",
                "scr_credit": 0.0,
                "scj_scr_mso": "必修",
                "scr_examid": "否",
                "scr_examfn": "否",
                "scr_exambf": "否",
                "cls_name": "經濟碩二",
                "scr_period": "(六)01     未排教室",
                "scr_precnt": 30.0,
                "scr_acptcnt": 6.0,
                "scr_remarks": " ",
                "unt_ls": 4106,
                "cls_id": "CB08320",
                "sub_id": "61530",
                "scr_dup": "001"
            },
            {
                "scr_selcode": "0591",
                "sub_id3": "ECON741",
                "sub_name": "產業經濟專題研究",
                "scr_credit": 3.0,
                "scj_scr_mso": "選修",
                "scr_examid": "否",
                "scr_examfn": "否",
                "scr_exambf": "否",
                "cls_name": "經濟碩二",
                "scr_period": "(三)02-04 商911 胡士文",
                "scr_precnt": 30.0,
                "scr_acptcnt": 10.0,
                "scr_remarks": null,
                "unt_ls": 4106,
                "cls_id": "CB08320",
                "sub_id": "41220",
                "scr_dup": "001"
            },
            {
                "scr_selcode": "0592",
                "sub_id3": "ITRA686",
                "sub_name": "國際貿易專題研究",
                "scr_credit": 3.0,
                "scj_scr_mso": "選修",
                "scr_examid": "否",
                "scr_examfn": "否",
                "scr_exambf": "否",
                "cls_name": "經濟碩二",
                "scr_period": "(二)07-09 商911 趙志鉅",
                "scr_precnt": 30.0,
                "scr_acptcnt": 12.0,
                "scr_remarks": null,
                "unt_ls": 4106,
                "cls_id": "CB08320",
                "sub_id": "43000",
                "scr_dup": "001"
            },
            {
                "scr_selcode": "3835",
                "sub_id3": "ECON748",
                "sub_name": "兩岸財經政策研究",
                "scr_credit": 3.0,
                "scj_scr_mso": "選修",
                "scr_examid": "否",
                "scr_examfn": "否",
                "scr_exambf": "否",
                "cls_name": "經濟碩二",
                "scr_period": "(二)02-04 商911 陳金發",
                "scr_precnt": 30.0,
                "scr_acptcnt": 8.0,
                "scr_remarks": null,
                "unt_ls": 4106,
                "cls_id": "CB08320",
                "sub_id": "22513",
                "scr_dup": "001"
            },
            {
                "scr_selcode": "0466",
                "sub_id3": "MGT612",
                "sub_name": "人力資源管理",
                "scr_credit": 3.0,
                "scj_scr_mso": "必修",
                "scr_examid": "否",
                "scr_examfn": "否",
                "scr_exambf": "否",
                "cls_name": "合經碩一",
                "scr_period": "(三)02-04 商907 林瑞發",
                "scr_precnt": 0.0,
                "scr_acptcnt": 14.0,
                "scr_remarks": " ",
                "unt_ls": 4107,
                "cls_id": "CB06310",
                "sub_id": "00690",
                "scr_dup": "001"
            },
            {
                "scr_selcode": "0467",
                "sub_id3": "COOP606",
                "sub_name": "合作經濟理論",
                "scr_credit": 3.0,
                "scj_scr_mso": "必修",
                "scr_examid": "否",
                "scr_examfn": "否",
                "scr_exambf": "否",
                "cls_name": "合經碩一",
                "scr_period": "(三)07-09 商907 李桂秋,吳肇展",
                "scr_precnt": 0.0,
                "scr_acptcnt": 13.0,
                "scr_remarks": " ",
                "unt_ls": 4107,
                "cls_id": "CB06310",
                "sub_id": "14572",
                "scr_dup": "001"
            },
            {
                "scr_selcode": "0468",
                "sub_id3": "MGT620",
                "sub_name": "行銷管理",
                "scr_credit": 3.0,
                "scj_scr_mso": "選修",
                "scr_examid": "否",
                "scr_examfn": "否",
                "scr_exambf": "否",
                "cls_name": "合經碩一",
                "scr_period": "(二)02-04 商907 江宜芳",
                "scr_precnt": 60.0,
                "scr_acptcnt": 15.0,
                "scr_remarks": null,
                "unt_ls": 4107,
                "cls_id": "CB06310",
                "sub_id": "14740",
                "scr_dup": "001"
            },
            {
                "scr_selcode": "0469",
                "sub_id3": "STAT605",
                "sub_name": "多變量分析",
                "scr_credit": 3.0,
                "scj_scr_mso": "選修",
                "scr_examid": "否",
                "scr_examfn": "否",
                "scr_exambf": "否",
                "cls_name": "合經碩一",
                "scr_period": "(四)02-04 商907 葉俐廷",
                "scr_precnt": 60.0,
                "scr_acptcnt": 10.0,
                "scr_remarks": null,
                "unt_ls": 4107,
                "cls_id": "CB06310",
                "sub_id": "19000",
                "scr_dup": "001"
            },
            {
                "scr_selcode": "0469",
                "sub_id3": "STAT605",
                "sub_name": "多變量分析",
                "scr_credit": 3.0,
                "scj_scr_mso": "選修",
                "scr_examid": "否",
                "scr_examfn": "否",
                "scr_exambf": "否",
                "cls_name": "合經專班碩一",
                "scr_period": "(四)02-04 商907 葉俐廷",
                "scr_precnt": 60.0,
                "scr_acptcnt": 10.0,
                "scr_remarks": null,
                "unt_ls": 4107,
                "cls_id": "CB0631A",
                "sub_id": "19000",
                "scr_dup": "001"
            },
            {
                "scr_selcode": "0470",
                "sub_id3": "COOP604",
                "sub_name": "企業倫理與社會責任",
                "scr_credit": 3.0,
                "scj_scr_mso": "必修",
                "scr_examid": "否",
                "scr_examfn": "否",
                "scr_exambf": "否",
                "cls_name": "合經碩二",
                "scr_period": "(六)02-04 商907 汪浩",
                "scr_precnt": 0.0,
                "scr_acptcnt": 16.0,
                "scr_remarks": " ",
                "unt_ls": 4107,
                "cls_id": "CB06320",
                "sub_id": "15915",
                "scr_dup": "001"
            },
            {
                "scr_selcode": "0471",
                "sub_id3": "COB601",
                "sub_name": "碩士論文",
                "scr_credit": 0.0,
                "scj_scr_mso": "必修",
                "scr_examid": "否",
                "scr_examfn": "否",
                "scr_exambf": "否",
                "cls_name": "合經碩二",
                "scr_period": " ",
                "scr_precnt": 0.0,
                "scr_acptcnt": 17.0,
                "scr_remarks": " ",
                "unt_ls": 4107,
                "cls_id": "CB06320",
                "sub_id": "61530",
                "scr_dup": "001"
            },
            {
                "scr_selcode": "0472",
                "sub_id3": "COOP673",
                "sub_name": "企業社會責任認證專題",
                "scr_credit": 3.0,
                "scj_scr_mso": "選修",
                "scr_examid": "否",
                "scr_examfn": "否",
                "scr_exambf": "否",
                "cls_name": "合經碩二",
                "scr_period": "(一)07-09 商907 汪浩",
                "scr_precnt": 60.0,
                "scr_acptcnt": 10.0,
                "scr_remarks": null,
                "unt_ls": 4107,
                "cls_id": "CB06320",
                "sub_id": "12981",
                "scr_dup": "001"
            },
            {
                "scr_selcode": "0473",
                "sub_id3": "COOP791",
                "sub_name": "產業專業實習(一)",
                "scr_credit": 3.0,
                "scj_scr_mso": "選修",
                "scr_examid": "否",
                "scr_examfn": "否",
                "scr_exambf": "否",
                "cls_name": "合經碩二",
                "scr_period": "(日)02-04 未排教室 吳肇展,葉俐廷",
                "scr_precnt": 60.0,
                "scr_acptcnt": 2.0,
                "scr_remarks": null,
                "unt_ls": 4107,
                "cls_id": "CB06320",
                "sub_id": "41315",
                "scr_dup": "001"
            },
            {
                "scr_selcode": "0474",
                "sub_id3": "COOP792",
                "sub_name": "產業專業實習(二)",
                "scr_credit": 3.0,
                "scj_scr_mso": "選修",
                "scr_examid": "否",
                "scr_examfn": "否",
                "scr_exambf": "否",
                "cls_name": "合經碩二",
                "scr_period": "(日)06-08 未排教室 江宜芳,梁欣光",
                "scr_precnt": 60.0,
                "scr_acptcnt": 2.0,
                "scr_remarks": null,
                "unt_ls": 4107,
                "cls_id": "CB06320",
                "sub_id": "41316",
                "scr_dup": "001"
            },
            {
                "scr_selcode": "0475",
                "sub_id3": "ECON740",
                "sub_name": "產業經濟學",
                "scr_credit": 3.0,
                "scj_scr_mso": "選修",
                "scr_examid": "否",
                "scr_examfn": "否",
                "scr_exambf": "否",
                "cls_name": "合經碩二",
                "scr_period": "(五)07-09 商907 簡正儀,陳聖賢",
                "scr_precnt": 60.0,
                "scr_acptcnt": 5.0,
                "scr_remarks": null,
                "unt_ls": 4107,
                "cls_id": "CB06320",
                "sub_id": "41340",
                "scr_dup": "001"
            },
            {
                "scr_selcode": "0606",
                "sub_id3": "ELAW602",
                "sub_name": "法律經濟學(二)",
                "scr_credit": 2.0,
                "scj_scr_mso": "必修",
                "scr_examid": "否",
                "scr_examfn": "否",
                "scr_exambf": "否",
                "cls_name": "財法碩一法律學組",
                "scr_period": "(四)03-04 商615 林問一",
                "scr_precnt": 30.0,
                "scr_acptcnt": 20.0,
                "scr_remarks": " ",
                "unt_ls": 4111,
                "cls_id": "CB15311",
                "sub_id": "30303",
                "scr_dup": "001"
            },
            {
                "scr_selcode": "0607",
                "sub_id3": "ELAW604",
                "sub_name": "法律倫理專題講座(二)",
                "scr_credit": 1.0,
                "scj_scr_mso": "必修",
                "scr_examid": "否",
                "scr_examfn": "否",
                "scr_exambf": "否",
                "cls_name": "財法碩一法律學組",
                "scr_period": "(四)07     商105(實習法庭) 林廷機",
                "scr_precnt": 20.0,
                "scr_acptcnt": 9.0,
                "scr_remarks": " ",
                "unt_ls": 4111,
                "cls_id": "CB15311",
                "sub_id": "30309",
                "scr_dup": "001"
            },
            {
                "scr_selcode": "0608",
                "sub_id3": "ELAW808",
                "sub_name": "法學英文（二）",
                "scr_credit": 2.0,
                "scj_scr_mso": "必修",
                "scr_examid": "否",
                "scr_examfn": "否",
                "scr_exambf": "否",
                "cls_name": "財法碩一法律學組",
                "scr_period": "(一)09-10 商615 林廷機",
                "scr_precnt": 20.0,
                "scr_acptcnt": 9.0,
                "scr_remarks": " ",
                "unt_ls": 4111,
                "cls_id": "CB15311",
                "sub_id": "30316",
                "scr_dup": "001"
            },
            {
                "scr_selcode": "0609",
                "sub_id3": "ELAW651",
                "sub_name": "公司治理專題研究",
                "scr_credit": 2.0,
                "scj_scr_mso": "選修",
                "scr_examid": "否",
                "scr_examfn": "否",
                "scr_exambf": "否",
                "cls_name": "財法碩一法律學組",
                "scr_period": "(三)09-10 商703 林問一",
                "scr_precnt": 30.0,
                "scr_acptcnt": 8.0,
                "scr_remarks": null,
                "unt_ls": 4111,
                "cls_id": "CB15311",
                "sub_id": "06306",
                "scr_dup": "001"
            },
            {
                "scr_selcode": "0610",
                "sub_id3": "ELAW634",
                "sub_name": "金融法專題研究",
                "scr_credit": 2.0,
                "scj_scr_mso": "選修",
                "scr_examid": "否",
                "scr_examfn": "否",
                "scr_exambf": "否",
                "cls_name": "財法碩一法律學組",
                "scr_period": "(三)07-08 商703 廖崇宏",
                "scr_precnt": 30.0,
                "scr_acptcnt": 21.0,
                "scr_remarks": null,
                "unt_ls": 4111,
                "cls_id": "CB15311",
                "sub_id": "22931",
                "scr_dup": "001"
            },
            {
                "scr_selcode": "0611",
                "sub_id3": "ELAW863",
                "sub_name": "原住民族法",
                "scr_credit": 2.0,
                "scj_scr_mso": "選修",
                "scr_examid": "否",
                "scr_examfn": "否",
                "scr_exambf": "否",
                "cls_name": "財法碩一法律學組",
                "scr_period": "(五)07-08 商703 林孟玲",
                "scr_precnt": 30.0,
                "scr_acptcnt": 14.0,
                "scr_remarks": null,
                "unt_ls": 4111,
                "cls_id": "CB15311",
                "sub_id": "83777",
                "scr_dup": "001"
            },
            {
                "scr_selcode": "0612",
                "sub_id3": "ELAW834",
                "sub_name": "個人資料保護法",
                "scr_credit": 2.0,
                "scj_scr_mso": "選修",
                "scr_examid": "否",
                "scr_examfn": "否",
                "scr_exambf": "否",
                "cls_name": "財法碩一法律學組",
                "scr_period": "(一)11-12 商703 林俊宏",
                "scr_precnt": 30.0,
                "scr_acptcnt": 18.0,
                "scr_remarks": null,
                "unt_ls": 4111,
                "cls_id": "CB15311",
                "sub_id": "96172",
                "scr_dup": "001"
            },
            {
                "scr_selcode": "0613",
                "sub_id3": "ELAW813",
                "sub_name": "民法債篇總論",
                "scr_credit": 2.0,
                "scj_scr_mso": "必修",
                "scr_examid": "否",
                "scr_examfn": "否",
                "scr_exambf": "否",
                "cls_name": "財法碩一法律專業組",
                "scr_period": "(四)03-04 商703 廖崇宏",
                "scr_precnt": 30.0,
                "scr_acptcnt": 8.0,
                "scr_remarks": " ",
                "unt_ls": 4111,
                "cls_id": "CB15312",
                "sub_id": "11098",
                "scr_dup": "001"
            },
            {
                "scr_selcode": "0614",
                "sub_id3": "ELAW713",
                "sub_name": "民法物權",
                "scr_credit": 2.0,
                "scj_scr_mso": "必修",
                "scr_examid": "否",
                "scr_examfn": "否",
                "scr_exambf": "否",
                "cls_name": "財法碩一法律專業組",
                "scr_period": "(三)11-12 商615 葉德輝",
                "scr_precnt": 30.0,
                "scr_acptcnt": 8.0,
                "scr_remarks": " ",
                "unt_ls": 4111,
                "cls_id": "CB15312",
                "sub_id": "11108",
                "scr_dup": "001"
            },
            {
                "scr_selcode": "0615",
                "sub_id3": "ELAW814",
                "sub_name": "行政法總論",
                "scr_credit": 2.0,
                "scj_scr_mso": "必修",
                "scr_examid": "否",
                "scr_examfn": "否",
                "scr_exambf": "否",
                "cls_name": "財法碩一法律專業組",
                "scr_period": "(二)03-04 商615 李東穎",
                "scr_precnt": 30.0,
                "scr_acptcnt": 3.0,
                "scr_remarks": " ",
                "unt_ls": 4111,
                "cls_id": "CB15312",
                "sub_id": "16401",
                "scr_dup": "001"
            },
            {
                "scr_selcode": "0616",
                "sub_id3": "ELAW715",
                "sub_name": "刑法分則",
                "scr_credit": 2.0,
                "scj_scr_mso": "必修",
                "scr_examid": "否",
                "scr_examfn": "否",
                "scr_exambf": "否",
                "cls_name": "財法碩一法律專業組",
                "scr_period": "(五)07-08 商615 蕭宏宜",
                "scr_precnt": 30.0,
                "scr_acptcnt": 6.0,
                "scr_remarks": " ",
                "unt_ls": 4111,
                "cls_id": "CB15312",
                "sub_id": "17390",
                "scr_dup": "001"
            },
            {
                "scr_selcode": "0617",
                "sub_id3": "ELAW831",
                "sub_name": "專業法學英文(二)",
                "scr_credit": 2.0,
                "scj_scr_mso": "必修",
                "scr_examid": "否",
                "scr_examfn": "否",
                "scr_exambf": "否",
                "cls_name": "財法碩一法律專業組",
                "scr_period": "(二)01-02 商615 林廷機",
                "scr_precnt": 20.0,
                "scr_acptcnt": 5.0,
                "scr_remarks": " ",
                "unt_ls": 4111,
                "cls_id": "CB15312",
                "sub_id": "82285",
                "scr_dup": "001"
            },
            {
                "scr_selcode": "0618",
                "sub_id3": "ELAW816",
                "sub_name": "勞動社會法",
                "scr_credit": 2.0,
                "scj_scr_mso": "選修",
                "scr_examid": "否",
                "scr_examfn": "否",
                "scr_exambf": "否",
                "cls_name": "財法碩一法律專業組",
                "scr_period": "(二)11-12 商105(實習法庭) 曹宗鼎",
                "scr_precnt": 30.0,
                "scr_acptcnt": 9.0,
                "scr_remarks": null,
                "unt_ls": 4111,
                "cls_id": "CB15312",
                "sub_id": "49948",
                "scr_dup": "001"
            },
            {
                "scr_selcode": "0619",
                "sub_id3": "ELAW861",
                "sub_name": "國家賠償法",
                "scr_credit": 2.0,
                "scj_scr_mso": "選修",
                "scr_examid": "否",
                "scr_examfn": "否",
                "scr_exambf": "否",
                "cls_name": "財法碩一法律專業組",
                "scr_period": "(四)01-02 商703 李東穎",
                "scr_precnt": 30.0,
                "scr_acptcnt": 7.0,
                "scr_remarks": null,
                "unt_ls": 4111,
                "cls_id": "CB15312",
                "sub_id": "81931",
                "scr_dup": "001"
            },
            {
                "scr_selcode": "0620",
                "sub_id3": "ELAW833",
                "sub_name": "實用法學英文(二)",
                "scr_credit": 2.0,
                "scj_scr_mso": "必修",
                "scr_examid": "否",
                "scr_examfn": "否",
                "scr_exambf": "否",
                "cls_name": "財法專碩一",
                "scr_period": "(一)11-12 商615 林廷機",
                "scr_precnt": 30.0,
                "scr_acptcnt": 14.0,
                "scr_remarks": " ",
                "unt_ls": 4111,
                "cls_id": "CB1531A",
                "sub_id": "82286",
                "scr_dup": "001"
            },
            {
                "scr_selcode": "0621",
                "sub_id3": "ELAW837",
                "sub_name": "法律與財經分析（二）",
                "scr_credit": 2.0,
                "scj_scr_mso": "必修",
                "scr_examid": "否",
                "scr_examfn": "否",
                "scr_exambf": "否",
                "cls_name": "財法專碩一",
                "scr_period": "(六)01-02 商615 林問一",
                "scr_precnt": 30.0,
                "scr_acptcnt": 15.0,
                "scr_remarks": " ",
                "unt_ls": 4111,
                "cls_id": "CB1531A",
                "sub_id": "98273",
                "scr_dup": "001"
            },
            {
                "scr_selcode": "0622",
                "sub_id3": "ELAW851",
                "sub_name": "法律倫理實務（二）",
                "scr_credit": 1.0,
                "scj_scr_mso": "必修",
                "scr_examid": "否",
                "scr_examfn": "否",
                "scr_exambf": "否",
                "cls_name": "財法專碩一",
                "scr_period": "(一)13     商615 林廷機",
                "scr_precnt": 30.0,
                "scr_acptcnt": 14.0,
                "scr_remarks": " ",
                "unt_ls": 4111,
                "cls_id": "CB1531A",
                "sub_id": "98274",
                "scr_dup": "001"
            },
            {
                "scr_selcode": "0623",
                "sub_id3": "ELAW864",
                "sub_name": "不動產及工程法律專題",
                "scr_credit": 2.0,
                "scj_scr_mso": "選修",
                "scr_examid": "否",
                "scr_examfn": "否",
                "scr_exambf": "否",
                "cls_name": "財法專碩一",
                "scr_period": "(日)07-08 商615 林俊宏",
                "scr_precnt": 30.0,
                "scr_acptcnt": 21.0,
                "scr_remarks": null,
                "unt_ls": 4111,
                "cls_id": "CB1531A",
                "sub_id": "06726",
                "scr_dup": "001"
            },
            {
                "scr_selcode": "0624",
                "sub_id3": "ELAW846",
                "sub_name": "智慧財產權管理與授權",
                "scr_credit": 2.0,
                "scj_scr_mso": "選修",
                "scr_examid": "否",
                "scr_examfn": "否",
                "scr_exambf": "否",
                "cls_name": "財法專碩一",
                "scr_period": "(六)03-04 商615 葉德輝",
                "scr_precnt": 30.0,
                "scr_acptcnt": 12.0,
                "scr_remarks": null,
                "unt_ls": 4111,
                "cls_id": "CB1531A",
                "sub_id": "67813",
                "scr_dup": "001"
            },
            {
                "scr_selcode": "0625",
                "sub_id3": "ELAW839",
                "sub_name": "財稅法",
                "scr_credit": 2.0,
                "scj_scr_mso": "選修",
                "scr_examid": "否",
                "scr_examfn": "否",
                "scr_exambf": "否",
                "cls_name": "財法專碩一",
                "scr_period": "(六)07-08 商105(實習法庭) 黃定遠,張升星",
                "scr_precnt": 30.0,
                "scr_acptcnt": 12.0,
                "scr_remarks": null,
                "unt_ls": 4111,
                "cls_id": "CB1531A",
                "sub_id": "82363",
                "scr_dup": "001"
            },
            {
                "scr_selcode": "0626",
                "sub_id3": "ELAW697",
                "sub_name": "碩士論文",
                "scr_credit": 0.0,
                "scj_scr_mso": "必修",
                "scr_examid": "否",
                "scr_examfn": "否",
                "scr_exambf": "否",
                "cls_name": "財法碩二法律學組",
                "scr_period": "(日)01     未排教室",
                "scr_precnt": 50.0,
                "scr_acptcnt": 29.0,
                "scr_remarks": " ",
                "unt_ls": 4111,
                "cls_id": "CB15321",
                "sub_id": "61530",
                "scr_dup": "001"
            },
            {
                "scr_selcode": "0627",
                "sub_id3": "FINA608",
                "sub_name": "金融商品與交易制度",
                "scr_credit": 3.0,
                "scj_scr_mso": "選修",
                "scr_examid": "否",
                "scr_examfn": "否",
                "scr_exambf": "否",
                "cls_name": "財法碩二法律學組",
                "scr_period": "(三)02-04 商703 林問一",
                "scr_precnt": 30.0,
                "scr_acptcnt": 9.0,
                "scr_remarks": null,
                "unt_ls": 4111,
                "cls_id": "CB15321",
                "sub_id": "22781",
                "scr_dup": "001"
            },
            {
                "scr_selcode": "0628",
                "sub_id3": "ELAW815",
                "sub_name": "法律專業倫理",
                "scr_credit": 2.0,
                "scj_scr_mso": "選修",
                "scr_examid": "否",
                "scr_examfn": "否",
                "scr_exambf": "否",
                "cls_name": "財法碩二法律學組",
                "scr_period": "(一)07-08 商105(實習法庭) 林廷機",
                "scr_precnt": 20.0,
                "scr_acptcnt": 11.0,
                "scr_remarks": null,
                "unt_ls": 4111,
                "cls_id": "CB15321",
                "sub_id": "30314",
                "scr_dup": "001"
            },
            {
                "scr_selcode": "0629",
                "sub_id3": "ELAW811",
                "sub_name": "國際通訊傳播法專題",
                "scr_credit": 2.0,
                "scj_scr_mso": "選修",
                "scr_examid": "否",
                "scr_examfn": "否",
                "scr_exambf": "否",
                "cls_name": "財法碩二法律學組",
                "scr_period": "(一)09-10 商703 林俊宏",
                "scr_precnt": 30.0,
                "scr_acptcnt": 13.0,
                "scr_remarks": null,
                "unt_ls": 4111,
                "cls_id": "CB15321",
                "sub_id": "41376",
                "scr_dup": "001"
            },
            {
                "scr_selcode": "0630",
                "sub_id3": "ELAW852",
                "sub_name": "法律專業實習(一)",
                "scr_credit": 1.0,
                "scj_scr_mso": "選修",
                "scr_examid": "否",
                "scr_examfn": "否",
                "scr_exambf": "否",
                "cls_name": "財法碩二法律學組",
                "scr_period": "(日)02     未排教室 林孟玲",
                "scr_precnt": 20.0,
                "scr_acptcnt": 4.0,
                "scr_remarks": null,
                "unt_ls": 4111,
                "cls_id": "CB15321",
                "sub_id": "81612",
                "scr_dup": "001"
            },
            {
                "scr_selcode": "0606",
                "sub_id3": "ELAW602",
                "sub_name": "法律經濟學(二)",
                "scr_credit": 2.0,
                "scj_scr_mso": "必修",
                "scr_examid": "否",
                "scr_examfn": "否",
                "scr_exambf": "否",
                "cls_name": "財法碩二法律專業組",
                "scr_period": "(四)03-04 商615 林問一",
                "scr_precnt": 30.0,
                "scr_acptcnt": 20.0,
                "scr_remarks": " ",
                "unt_ls": 4111,
                "cls_id": "CB15322",
                "sub_id": "30303",
                "scr_dup": "001"
            },
            {
                "scr_selcode": "0628",
                "sub_id3": "ELAW815",
                "sub_name": "法律專業倫理",
                "scr_credit": 2.0,
                "scj_scr_mso": "選修",
                "scr_examid": "否",
                "scr_examfn": "否",
                "scr_exambf": "否",
                "cls_name": "財法碩二法律專業組",
                "scr_period": "(一)07-08 商105(實習法庭) 林廷機",
                "scr_precnt": 20.0,
                "scr_acptcnt": 11.0,
                "scr_remarks": null,
                "unt_ls": 4111,
                "cls_id": "CB15322",
                "sub_id": "30314",
                "scr_dup": "001"
            },
            {
                "scr_selcode": "0632",
                "sub_id3": "ELAW722",
                "sub_name": "民事訴訟法(二)",
                "scr_credit": 2.0,
                "scj_scr_mso": "必修",
                "scr_examid": "否",
                "scr_examfn": "否",
                "scr_exambf": "否",
                "cls_name": "財法碩二法律專業組",
                "scr_period": "(五)02-03 商105(實習法庭) 張升星",
                "scr_precnt": 30.0,
                "scr_acptcnt": 11.0,
                "scr_remarks": " ",
                "unt_ls": 4111,
                "cls_id": "CB15322",
                "sub_id": "11092",
                "scr_dup": "001"
            },
            {
                "scr_selcode": "0633",
                "sub_id3": "ELAW727",
                "sub_name": "刑事訴訟法(二)",
                "scr_credit": 2.0,
                "scj_scr_mso": "必修",
                "scr_examid": "否",
                "scr_examfn": "否",
                "scr_exambf": "否",
                "cls_name": "財法碩二法律專業組",
                "scr_period": "(二)01-02 商703 洪文章",
                "scr_precnt": 30.0,
                "scr_acptcnt": 10.0,
                "scr_remarks": " ",
                "unt_ls": 4111,
                "cls_id": "CB15322",
                "sub_id": "17391",
                "scr_dup": "001"
            },
            {
                "scr_selcode": "0634",
                "sub_id3": "ELAW604",
                "sub_name": "法律倫理專題講座(二)",
                "scr_credit": 1.0,
                "scj_scr_mso": "必修",
                "scr_examid": "否",
                "scr_examfn": "否",
                "scr_exambf": "否",
                "cls_name": "財法碩二法律專業組",
                "scr_period": "(四)08     商105(實習法庭) 林廷機",
                "scr_precnt": 20.0,
                "scr_acptcnt": 10.0,
                "scr_remarks": " ",
                "unt_ls": 4111,
                "cls_id": "CB15322",
                "sub_id": "30309",
                "scr_dup": "001"
            },
            {
                "scr_selcode": "0635",
                "sub_id3": "ELAW724",
                "sub_name": "實習法庭(二)",
                "scr_credit": 1.0,
                "scj_scr_mso": "必修",
                "scr_examid": "否",
                "scr_examfn": "否",
                "scr_exambf": "否",
                "cls_name": "財法碩二法律專業組",
                "scr_period": "(五)04     商105(實習法庭) 張升星",
                "scr_precnt": 30.0,
                "scr_acptcnt": 11.0,
                "scr_remarks": " ",
                "unt_ls": 4111,
                "cls_id": "CB15322",
                "sub_id": "67196",
                "scr_dup": "001"
            },
            {
                "scr_selcode": "0636",
                "sub_id3": "ELAW828",
                "sub_name": "金融法",
                "scr_credit": 2.0,
                "scj_scr_mso": "選修",
                "scr_examid": "否",
                "scr_examfn": "否",
                "scr_exambf": "否",
                "cls_name": "財法碩二法律專業組",
                "scr_period": "(二)07-08 商703 廖崇宏",
                "scr_precnt": 30.0,
                "scr_acptcnt": 14.0,
                "scr_remarks": null,
                "unt_ls": 4111,
                "cls_id": "CB15322",
                "sub_id": "22933",
                "scr_dup": "001"
            },
            {
                "scr_selcode": "0637",
                "sub_id3": "ELAW697",
                "sub_name": "碩士論文",
                "scr_credit": 0.0,
                "scj_scr_mso": "必修",
                "scr_examid": "否",
                "scr_examfn": "否",
                "scr_exambf": "否",
                "cls_name": "財法專碩二",
                "scr_period": "(日)01     未排教室",
                "scr_precnt": 50.0,
                "scr_acptcnt": 27.0,
                "scr_remarks": " ",
                "unt_ls": 4111,
                "cls_id": "CB1532A",
                "sub_id": "61530",
                "scr_dup": "001"
            },
            {
                "scr_selcode": "0638",
                "sub_id3": "ELAW858",
                "sub_name": "民事訴訟法及民事訴訟實務",
                "scr_credit": 2.0,
                "scj_scr_mso": "選修",
                "scr_examid": "否",
                "scr_examfn": "否",
                "scr_exambf": "否",
                "cls_name": "財法專碩二",
                "scr_period": "(六)09-10 商105(實習法庭) 張升星",
                "scr_precnt": 30.0,
                "scr_acptcnt": 8.0,
                "scr_remarks": null,
                "unt_ls": 4111,
                "cls_id": "CB1532A",
                "sub_id": "11117",
                "scr_dup": "001"
            },
            {
                "scr_selcode": "0639",
                "sub_id3": "ELAW843",
                "sub_name": "生物科技法與永續發展產業專題",
                "scr_credit": 2.0,
                "scj_scr_mso": "選修",
                "scr_examid": "否",
                "scr_examfn": "否",
                "scr_exambf": "否",
                "cls_name": "財法專碩二",
                "scr_period": "(六)01-02 商703 林孟玲,王偉霖",
                "scr_precnt": 30.0,
                "scr_acptcnt": 6.0,
                "scr_remarks": null,
                "unt_ls": 4111,
                "cls_id": "CB1532A",
                "sub_id": "12717",
                "scr_dup": "001"
            },
            {
                "scr_selcode": "0640",
                "sub_id3": "ELAW847",
                "sub_name": "金融法與保險法",
                "scr_credit": 2.0,
                "scj_scr_mso": "選修",
                "scr_examid": "否",
                "scr_examfn": "否",
                "scr_exambf": "否",
                "cls_name": "財法專碩二",
                "scr_period": "(六)03-04 商703 廖崇宏",
                "scr_precnt": 30.0,
                "scr_acptcnt": 8.0,
                "scr_remarks": null,
                "unt_ls": 4111,
                "cls_id": "CB1532A",
                "sub_id": "22951",
                "scr_dup": "001"
            },
            {
                "scr_selcode": "0641",
                "sub_id3": "ELAW842",
                "sub_name": "海商法與海洋法",
                "scr_credit": 2.0,
                "scj_scr_mso": "選修",
                "scr_examid": "否",
                "scr_examfn": "否",
                "scr_exambf": "否",
                "cls_name": "財法專碩二",
                "scr_period": "(日)03-04 商615 林俊宏",
                "scr_precnt": 30.0,
                "scr_acptcnt": 18.0,
                "scr_remarks": null,
                "unt_ls": 4111,
                "cls_id": "CB1532A",
                "sub_id": "37202",
                "scr_dup": "001"
            },
            {
                "scr_selcode": "0612",
                "sub_id3": "ELAW834",
                "sub_name": "個人資料保護法",
                "scr_credit": 2.0,
                "scj_scr_mso": "選修",
                "scr_examid": "否",
                "scr_examfn": "否",
                "scr_exambf": "否",
                "cls_name": "財法碩三法律專業組",
                "scr_period": "(一)11-12 商703 林俊宏",
                "scr_precnt": 30.0,
                "scr_acptcnt": 18.0,
                "scr_remarks": null,
                "unt_ls": 4111,
                "cls_id": "CB15332",
                "sub_id": "96172",
                "scr_dup": "001"
            },
            {
                "scr_selcode": "0626",
                "sub_id3": "ELAW697",
                "sub_name": "碩士論文",
                "scr_credit": 0.0,
                "scj_scr_mso": "必修",
                "scr_examid": "否",
                "scr_examfn": "否",
                "scr_exambf": "否",
                "cls_name": "財法碩三法律專業組",
                "scr_period": "(日)01     未排教室",
                "scr_precnt": 50.0,
                "scr_acptcnt": 29.0,
                "scr_remarks": " ",
                "unt_ls": 4111,
                "cls_id": "CB15332",
                "sub_id": "61530",
                "scr_dup": "001"
            },
            {
                "scr_selcode": "0630",
                "sub_id3": "ELAW852",
                "sub_name": "法律專業實習(一)",
                "scr_credit": 1.0,
                "scj_scr_mso": "選修",
                "scr_examid": "否",
                "scr_examfn": "否",
                "scr_exambf": "否",
                "cls_name": "財法碩三法律專業組",
                "scr_period": "(日)02     未排教室 林孟玲",
                "scr_precnt": 20.0,
                "scr_acptcnt": 4.0,
                "scr_remarks": null,
                "unt_ls": 4111,
                "cls_id": "CB15332",
                "sub_id": "81612",
                "scr_dup": "001"
            },
            {
                "scr_selcode": "0650",
                "sub_id3": "MOT601",
                "sub_name": "科技專案管理",
                "scr_credit": 3.0,
                "scj_scr_mso": "必修",
                "scr_examid": "否",
                "scr_examfn": "否",
                "scr_exambf": "否",
                "cls_name": "科管碩一學位學程",
                "scr_period": "(四)07-09 商703 賴文祥",
                "scr_precnt": 20.0,
                "scr_acptcnt": 11.0,
                "scr_remarks": " ",
                "unt_ls": 4114,
                "cls_id": "CB21310",
                "sub_id": "22663",
                "scr_dup": "001"
            },
            {
                "scr_selcode": "0651",
                "sub_id3": "MOT633",
                "sub_name": "創新與創業",
                "scr_credit": 3.0,
                "scj_scr_mso": "必修",
                "scr_examid": "否",
                "scr_examfn": "否",
                "scr_exambf": "否",
                "cls_name": "科管碩一學位學程",
                "scr_period": "(二)02-04 商705 許瓊文",
                "scr_precnt": 20.0,
                "scr_acptcnt": 10.0,
                "scr_remarks": " ",
                "unt_ls": 4114,
                "cls_id": "CB21310",
                "sub_id": "50931",
                "scr_dup": "001"
            },
            {
                "scr_selcode": "0652",
                "sub_id3": "MOT631",
                "sub_name": "企業流程設計與管理",
                "scr_credit": 3.0,
                "scj_scr_mso": "選修",
                "scr_examid": "否",
                "scr_examfn": "否",
                "scr_exambf": "否",
                "cls_name": "科管碩一學位學程",
                "scr_period": "(二)06-08 商501 仇介民",
                "scr_precnt": 20.0,
                "scr_acptcnt": 13.0,
                "scr_remarks": null,
                "unt_ls": 4114,
                "cls_id": "CB21310",
                "sub_id": "12992",
                "scr_dup": "001"
            },
            {
                "scr_selcode": "0653",
                "sub_id3": "MOT654",
                "sub_name": "科技分析與專利佈局",
                "scr_credit": 3.0,
                "scj_scr_mso": "選修",
                "scr_examid": "否",
                "scr_examfn": "否",
                "scr_exambf": "否",
                "cls_name": "科管碩一學位學程",
                "scr_period": "(三)06-08 商501 仇介民",
                "scr_precnt": 20.0,
                "scr_acptcnt": 8.0,
                "scr_remarks": "智慧財產權暨技術移轉碩士學分學程",
                "unt_ls": 4114,
                "cls_id": "CB21310",
                "sub_id": "22626",
                "scr_dup": "001"
            },
            {
                "scr_selcode": "0655",
                "sub_id3": "MOT634",
                "sub_name": "創業財務",
                "scr_credit": 3.0,
                "scj_scr_mso": "選修",
                "scr_examid": "否",
                "scr_examfn": "否",
                "scr_exambf": "否",
                "cls_name": "科管碩一學位學程",
                "scr_period": "(三)02-04 商503 顏上詠",
                "scr_precnt": 20.0,
                "scr_acptcnt": 8.0,
                "scr_remarks": null,
                "unt_ls": 4114,
                "cls_id": "CB21310",
                "sub_id": "50201",
                "scr_dup": "001"
            },
            {
                "scr_selcode": "0656",
                "sub_id3": "COB601",
                "sub_name": "碩士論文",
                "scr_credit": 0.0,
                "scj_scr_mso": "必修",
                "scr_examid": "否",
                "scr_examfn": "否",
                "scr_exambf": "否",
                "cls_name": "科管碩二學位學程",
                "scr_period": " ",
                "scr_precnt": 0.0,
                "scr_acptcnt": 10.0,
                "scr_remarks": " ",
                "unt_ls": 4114,
                "cls_id": "CB21320",
                "sub_id": "61530",
                "scr_dup": "001"
            },
            {
                "scr_selcode": "0657",
                "sub_id3": "MOT687",
                "sub_name": "產業實習",
                "scr_credit": 3.0,
                "scj_scr_mso": "選修",
                "scr_examid": "否",
                "scr_examfn": "否",
                "scr_exambf": "否",
                "cls_name": "科管碩二學位學程",
                "scr_period": "(五)11-13 商527 黃禮林",
                "scr_precnt": 20.0,
                "scr_acptcnt": 1.0,
                "scr_remarks": null,
                "unt_ls": 4114,
                "cls_id": "CB21320",
                "sub_id": "41305",
                "scr_dup": "001"
            },
            {
                "scr_selcode": "0781",
                "sub_id3": "BM620",
                "sub_name": "世界經濟與中國趨勢",
                "scr_credit": 3.0,
                "scj_scr_mso": "必修",
                "scr_examid": "否",
                "scr_examfn": "否",
                "scr_exambf": "否",
                "cls_name": "商學專業碩專一學位學程",
                "scr_period": "(六)02-04 人203 高承恕,董正玫",
                "scr_precnt": 30.0,
                "scr_acptcnt": 20.0,
                "scr_remarks": "限商學專業碩士在職學位學程學生修習",
                "unt_ls": 4135,
                "cls_id": "CB3631A",
                "sub_id": "10793",
                "scr_dup": "001"
            },
            {
                "scr_selcode": "0782",
                "sub_id3": "BM631",
                "sub_name": "兩岸租稅專題",
                "scr_credit": 3.0,
                "scj_scr_mso": "選修",
                "scr_examid": "否",
                "scr_examfn": "否",
                "scr_exambf": "否",
                "cls_name": "商學專業碩專一學位學程",
                "scr_period": "(六)09-11 商804B 洪國仁",
                "scr_precnt": 30.0,
                "scr_acptcnt": 20.0,
                "scr_remarks": "限商學專業碩士在職學位學程學生修習",
                "unt_ls": 4135,
                "cls_id": "CB3631A",
                "sub_id": "22123",
                "scr_dup": "001"
            },
            {
                "scr_selcode": "0784",
                "sub_id3": "BM640",
                "sub_name": "審計與公司治理",
                "scr_credit": 3.0,
                "scj_scr_mso": "選修",
                "scr_examid": "否",
                "scr_examfn": "否",
                "scr_exambf": "否",
                "cls_name": "商學專業碩專一學位學程",
                "scr_period": "(六)06-08 商804B 林慶隆",
                "scr_precnt": 30.0,
                "scr_acptcnt": 20.0,
                "scr_remarks": "限商學專業碩士在職學位學程學生修習",
                "unt_ls": 4135,
                "cls_id": "CB3631A",
                "sub_id": "67856",
                "scr_dup": "001"
            },
            {
                "scr_selcode": "0785",
                "sub_id3": "BM625",
                "sub_name": "商務談判與產業發展專題",
                "scr_credit": 3.0,
                "scj_scr_mso": "必修",
                "scr_examid": "否",
                "scr_examfn": "否",
                "scr_exambf": "否",
                "cls_name": "商學專業碩專二學位學程",
                "scr_period": "(六)02-04 商804A 翁慈青",
                "scr_precnt": 35.0,
                "scr_acptcnt": 20.0,
                "scr_remarks": "限商學專業碩士在職學位學程學生修習",
                "unt_ls": 4135,
                "cls_id": "CB3632A",
                "sub_id": "31348",
                "scr_dup": "001"
            },
            {
                "scr_selcode": "0786",
                "sub_id3": "BM601",
                "sub_name": "碩士論文",
                "scr_credit": 0.0,
                "scj_scr_mso": "必修",
                "scr_examid": "否",
                "scr_examfn": "否",
                "scr_exambf": "否",
                "cls_name": "商學專業碩專二學位學程",
                "scr_period": " ",
                "scr_precnt": 60.0,
                "scr_acptcnt": 20.0,
                "scr_remarks": " ",
                "unt_ls": 4135,
                "cls_id": "CB3632A",
                "sub_id": "61530",
                "scr_dup": "001"
            },
            {
                "scr_selcode": "0787",
                "sub_id3": "BM655",
                "sub_name": "合作與社會企業專題",
                "scr_credit": 3.0,
                "scj_scr_mso": "選修",
                "scr_examid": "否",
                "scr_examfn": "否",
                "scr_exambf": "否",
                "cls_name": "商學專業碩專二學位學程",
                "scr_period": "(六)06-08 商804A 吳肇展",
                "scr_precnt": 30.0,
                "scr_acptcnt": 4.0,
                "scr_remarks": "限商學專業碩士在職學位學程學生修習",
                "unt_ls": 4135,
                "cls_id": "CB3632A",
                "sub_id": "13913",
                "scr_dup": "001"
            }
        ]
    }
}