{
    "d": {
        "message": "",
        "total": 33,
        "items": [
            {
                "scr_selcode": "0315",
                "sub_id3": "FINA673",
                "sub_name": "公司財務",
                "scr_credit": 3.0,
                "scj_scr_mso": "必修",
                "scr_examid": "否",
                "scr_examfn": "否",
                "scr_exambf": "否",
                "cls_name": "財金碩一",
                "scr_period": "(二)08-10 商1215 楊明晶",
                "scr_precnt": 25.0,
                "scr_acptcnt": 15.0,
                "scr_remarks": " ",
                "unt_ls": 4801,
                "cls_id": "CB03310",
                "sub_id": "06420",
                "scr_dup": "001"
            },
            {
                "scr_selcode": "0316",
                "sub_id3": "FINA650",
                "sub_name": "投資管理",
                "scr_credit": 3.0,
                "scj_scr_mso": "必修",
                "scr_examid": "否",
                "scr_examfn": "否",
                "scr_exambf": "否",
                "cls_name": "財金碩一",
                "scr_period": "(一)02-04 商512 王佳真",
                "scr_precnt": 25.0,
                "scr_acptcnt": 18.0,
                "scr_remarks": " ",
                "unt_ls": 4801,
                "cls_id": "CB03310",
                "sub_id": "18690",
                "scr_dup": "001"
            },
            {
                "scr_selcode": "0317",
                "sub_id3": "ECON631",
                "sub_name": "計量經濟學(一)",
                "scr_credit": 3.0,
                "scj_scr_mso": "必修",
                "scr_examid": "否",
                "scr_examfn": "否",
                "scr_exambf": "否",
                "cls_name": "財金碩一",
                "scr_period": "(五)02-04 商1215 廖東亮",
                "scr_precnt": 25.0,
                "scr_acptcnt": 16.0,
                "scr_remarks": " ",
                "unt_ls": 4801,
                "cls_id": "CB03310",
                "sub_id": "28310",
                "scr_dup": "001"
            },
            {
                "scr_selcode": "0318",
                "sub_id3": "FINA695",
                "sub_name": "論文研討(一)",
                "scr_credit": 1.0,
                "scj_scr_mso": "必修",
                "scr_examid": "否",
                "scr_examfn": "否",
                "scr_exambf": "否",
                "cls_name": "財金碩一",
                "scr_period": "(四)07     商512 陳清和",
                "scr_precnt": 25.0,
                "scr_acptcnt": 16.0,
                "scr_remarks": " ",
                "unt_ls": 4801,
                "cls_id": "CB03310",
                "sub_id": "68801",
                "scr_dup": "001"
            },
            {
                "scr_selcode": "0320",
                "sub_id3": "FINA652",
                "sub_name": "證券市場機制與行為",
                "scr_credit": 3.0,
                "scj_scr_mso": "選修",
                "scr_examid": "否",
                "scr_examfn": "否",
                "scr_exambf": "否",
                "cls_name": "財金碩一",
                "scr_period": "(四)02-04 商1215 簡正儀",
                "scr_precnt": 25.0,
                "scr_acptcnt": 15.0,
                "scr_remarks": null,
                "unt_ls": 4801,
                "cls_id": "CB03310",
                "sub_id": "76442",
                "scr_dup": "001"
            },
            {
                "scr_selcode": "0321",
                "sub_id3": "COB601",
                "sub_name": "碩士論文",
                "scr_credit": 0.0,
                "scj_scr_mso": "必修",
                "scr_examid": "否",
                "scr_examfn": "否",
                "scr_exambf": "否",
                "cls_name": "財金碩二",
                "scr_period": "(六)00     未排教室",
                "scr_precnt": 30.0,
                "scr_acptcnt": 17.0,
                "scr_remarks": " ",
                "unt_ls": 4801,
                "cls_id": "CB03320",
                "sub_id": "61530",
                "scr_dup": "001"
            },
            {
                "scr_selcode": "0323",
                "sub_id3": "INSU676",
                "sub_name": "財務風險管理",
                "scr_credit": 3.0,
                "scj_scr_mso": "選修",
                "scr_examid": "否",
                "scr_examfn": "否",
                "scr_exambf": "否",
                "cls_name": "財金碩二",
                "scr_period": "(一)02-04 商1215 李君屏",
                "scr_precnt": 15.0,
                "scr_acptcnt": 5.0,
                "scr_remarks": null,
                "unt_ls": 4801,
                "cls_id": "CB03320",
                "sub_id": "37735",
                "scr_dup": "001"
            },
            {
                "scr_selcode": "0324",
                "sub_id3": "FINA677",
                "sub_name": "財務經濟學計量模型",
                "scr_credit": 3.0,
                "scj_scr_mso": "選修",
                "scr_examid": "否",
                "scr_examfn": "否",
                "scr_exambf": "否",
                "cls_name": "財金碩二",
                "scr_period": "(二)11-13 商1215 張倉耀",
                "scr_precnt": 25.0,
                "scr_acptcnt": 30.0,
                "scr_remarks": null,
                "unt_ls": 4801,
                "cls_id": "CB03320",
                "sub_id": "37878",
                "scr_dup": "001"
            },
            {
                "scr_selcode": "0325",
                "sub_id3": "FINA678",
                "sub_name": "財務預測",
                "scr_credit": 3.0,
                "scj_scr_mso": "選修",
                "scr_examid": "否",
                "scr_examfn": "否",
                "scr_exambf": "否",
                "cls_name": "財金碩二",
                "scr_period": "(三)02-04 商1215 陳麗君",
                "scr_precnt": 15.0,
                "scr_acptcnt": 14.0,
                "scr_remarks": null,
                "unt_ls": 4801,
                "cls_id": "CB03320",
                "sub_id": "37961",
                "scr_dup": "001"
            },
            {
                "scr_selcode": "0326",
                "sub_id3": "FINA621",
                "sub_name": "財務工程",
                "scr_credit": 3.0,
                "scj_scr_mso": "選修",
                "scr_examid": "否",
                "scr_examfn": "否",
                "scr_exambf": "否",
                "cls_name": "財金碩二",
                "scr_period": "(三)07-09 商1215 許溪南",
                "scr_precnt": 15.0,
                "scr_acptcnt": 19.0,
                "scr_remarks": null,
                "unt_ls": 4801,
                "cls_id": "CB03320",
                "sub_id": "38210",
                "scr_dup": "001"
            },
            {
                "scr_selcode": "0327",
                "sub_id3": "FINA692",
                "sub_name": "銀行理論與實證",
                "scr_credit": 3.0,
                "scj_scr_mso": "選修",
                "scr_examid": "否",
                "scr_examfn": "否",
                "scr_exambf": "否",
                "cls_name": "財金碩二",
                "scr_period": "(一)06-08 商1215 林昆立",
                "scr_precnt": 15.0,
                "scr_acptcnt": 13.0,
                "scr_remarks": null,
                "unt_ls": 4801,
                "cls_id": "CB03320",
                "sub_id": "65602",
                "scr_dup": "001"
            },
            {
                "scr_selcode": "0390",
                "sub_id3": "ECON634",
                "sub_name": "計量經濟學",
                "scr_credit": 3.0,
                "scj_scr_mso": "必修",
                "scr_examid": "否",
                "scr_examfn": "否",
                "scr_exambf": "否",
                "cls_name": "風管與保險碩一",
                "scr_period": "(四)02-04 商1009 張吉宏",
                "scr_precnt": 20.0,
                "scr_acptcnt": 20.0,
                "scr_remarks": " ",
                "unt_ls": 4802,
                "cls_id": "CB04310",
                "sub_id": "28300",
                "scr_dup": "001"
            },
            {
                "scr_selcode": "0391",
                "sub_id3": "FINA630",
                "sub_name": "財務管理",
                "scr_credit": 3.0,
                "scj_scr_mso": "必修",
                "scr_examid": "否",
                "scr_examfn": "否",
                "scr_exambf": "否",
                "cls_name": "風管與保險碩一",
                "scr_period": "(三)02-04 商1009 朱心蘅",
                "scr_precnt": 20.0,
                "scr_acptcnt": 19.0,
                "scr_remarks": " ",
                "unt_ls": 4802,
                "cls_id": "CB04310",
                "sub_id": "37750",
                "scr_dup": "001"
            },
            {
                "scr_selcode": "0392",
                "sub_id3": "INSU620",
                "sub_name": "年金保險",
                "scr_credit": 3.0,
                "scj_scr_mso": "選修",
                "scr_examid": "否",
                "scr_examfn": "否",
                "scr_exambf": "否",
                "cls_name": "風管與保險碩一",
                "scr_period": "(二)06-08 商1009 林麗芬",
                "scr_precnt": 20.0,
                "scr_acptcnt": 24.0,
                "scr_remarks": null,
                "unt_ls": 4802,
                "cls_id": "CB04310",
                "sub_id": "18010",
                "scr_dup": "001"
            },
            {
                "scr_selcode": "0393",
                "sub_id3": "INSU641",
                "sub_name": "保險監理制度",
                "scr_credit": 2.0,
                "scj_scr_mso": "選修",
                "scr_examid": "否",
                "scr_examfn": "否",
                "scr_exambf": "否",
                "cls_name": "風管與保險碩一",
                "scr_period": "(一)03-04 商1007 鄭濟世",
                "scr_precnt": 20.0,
                "scr_acptcnt": 13.0,
                "scr_remarks": null,
                "unt_ls": 4802,
                "cls_id": "CB04310",
                "sub_id": "29020",
                "scr_dup": "001"
            },
            {
                "scr_selcode": "4424",
                "sub_id3": "INSU642",
                "sub_name": "壽險數學",
                "scr_credit": 3.0,
                "scj_scr_mso": "選修",
                "scr_examid": "否",
                "scr_examfn": "否",
                "scr_exambf": "否",
                "cls_name": "風管與保險碩一",
                "scr_period": "(三)07-09 商1007 張智凱",
                "scr_precnt": 15.0,
                "scr_acptcnt": 12.0,
                "scr_remarks": null,
                "unt_ls": 4802,
                "cls_id": "CB04310",
                "sub_id": "65800",
                "scr_dup": "001"
            },
            {
                "scr_selcode": "4434",
                "sub_id3": "FINA635",
                "sub_name": "財務專題(一)",
                "scr_credit": 3.0,
                "scj_scr_mso": "必修",
                "scr_examid": "否",
                "scr_examfn": "否",
                "scr_exambf": "否",
                "cls_name": "風管與保險碩一",
                "scr_period": "(四)07-09 商1009 張智凱",
                "scr_precnt": 15.0,
                "scr_acptcnt": 8.0,
                "scr_remarks": null,
                "unt_ls": 4802,
                "cls_id": "CB04310",
                "sub_id": "37886",
                "scr_dup": "001"
            },
            {
                "scr_selcode": "0394",
                "sub_id3": "INSU691",
                "sub_name": "專題討論(一)",
                "scr_credit": 1.0,
                "scj_scr_mso": "必修",
                "scr_examid": "否",
                "scr_examfn": "否",
                "scr_exambf": "否",
                "cls_name": "風管與保險碩二",
                "scr_period": "(二)03     商1009 劉純之",
                "scr_precnt": 20.0,
                "scr_acptcnt": 16.0,
                "scr_remarks": " ",
                "unt_ls": 4802,
                "cls_id": "CB04320",
                "sub_id": "43130",
                "scr_dup": "001"
            },
            {
                "scr_selcode": "0395",
                "sub_id3": "COB601",
                "sub_name": "碩士論文",
                "scr_credit": 0.0,
                "scj_scr_mso": "必修",
                "scr_examid": "是",
                "scr_examfn": "是",
                "scr_exambf": "否",
                "cls_name": "風管與保險碩二",
                "scr_period": " ",
                "scr_precnt": 60.0,
                "scr_acptcnt": 16.0,
                "scr_remarks": " ",
                "unt_ls": 4802,
                "cls_id": "CB04320",
                "sub_id": "61530",
                "scr_dup": "001"
            },
            {
                "scr_selcode": "0396",
                "sub_id3": "INSU698",
                "sub_name": "公司治理",
                "scr_credit": 3.0,
                "scj_scr_mso": "選修",
                "scr_examid": "否",
                "scr_examfn": "否",
                "scr_exambf": "否",
                "cls_name": "風管與保險碩二",
                "scr_period": "(三)06-08 商1009 曾鹿鳴,黃依潔,劉純之",
                "scr_precnt": 20.0,
                "scr_acptcnt": 10.0,
                "scr_remarks": null,
                "unt_ls": 4802,
                "cls_id": "CB04320",
                "sub_id": "06304",
                "scr_dup": "001"
            },
            {
                "scr_selcode": "0397",
                "sub_id3": "INSU603",
                "sub_name": "保險財務",
                "scr_credit": 3.0,
                "scj_scr_mso": "選修",
                "scr_examid": "否",
                "scr_examfn": "否",
                "scr_exambf": "否",
                "cls_name": "風管與保險碩二",
                "scr_period": "(二)07-09 商1007 呂瑞秋",
                "scr_precnt": 20.0,
                "scr_acptcnt": 12.0,
                "scr_remarks": null,
                "unt_ls": 4802,
                "cls_id": "CB04320",
                "sub_id": "29051",
                "scr_dup": "001"
            },
            {
                "scr_selcode": "0398",
                "sub_id3": "INSU617",
                "sub_name": "財產保險業務經營",
                "scr_credit": 2.0,
                "scj_scr_mso": "選修",
                "scr_examid": "否",
                "scr_examfn": "否",
                "scr_exambf": "否",
                "cls_name": "風管與保險碩二",
                "scr_period": "(一)03-04 商1009 鄒政下",
                "scr_precnt": 20.0,
                "scr_acptcnt": 8.0,
                "scr_remarks": null,
                "unt_ls": 4802,
                "cls_id": "CB04320",
                "sub_id": "37829",
                "scr_dup": "001"
            },
            {
                "scr_selcode": "0399",
                "sub_id3": "INSU657",
                "sub_name": "財產保險研究(二)",
                "scr_credit": 3.0,
                "scj_scr_mso": "選修",
                "scr_examid": "否",
                "scr_examfn": "否",
                "scr_exambf": "否",
                "cls_name": "風管與保險碩二",
                "scr_period": "(一)07-09 商1009 吳瑞雲",
                "scr_precnt": 20.0,
                "scr_acptcnt": 10.0,
                "scr_remarks": null,
                "unt_ls": 4802,
                "cls_id": "CB04320",
                "sub_id": "38072",
                "scr_dup": "001"
            },
            {
                "scr_selcode": "2226",
                "sub_id3": "INSU670",
                "sub_name": "風險管理",
                "scr_credit": 3.0,
                "scj_scr_mso": "必修",
                "scr_examid": "是",
                "scr_examfn": "是",
                "scr_exambf": "否",
                "cls_name": "金融專班碩一",
                "scr_period": "(六)02-04 商404 江朝峯",
                "scr_precnt": 40.0,
                "scr_acptcnt": 24.0,
                "scr_remarks": " ",
                "unt_ls": 4804,
                "cls_id": "CF0131A",
                "sub_id": "30620",
                "scr_dup": "001"
            },
            {
                "scr_selcode": "2227",
                "sub_id3": "FINA630",
                "sub_name": "財務管理",
                "scr_credit": 3.0,
                "scj_scr_mso": "必修",
                "scr_examid": "是",
                "scr_examfn": "是",
                "scr_exambf": "否",
                "cls_name": "金融專班碩一",
                "scr_period": "(日)02-04 商403 林昆立",
                "scr_precnt": 40.0,
                "scr_acptcnt": 22.0,
                "scr_remarks": " ",
                "unt_ls": 4804,
                "cls_id": "CF0131A",
                "sub_id": "37750",
                "scr_dup": "001"
            },
            {
                "scr_selcode": "2228",
                "sub_id3": "FINA600",
                "sub_name": "金融機構經營與管理",
                "scr_credit": 3.0,
                "scj_scr_mso": "選修",
                "scr_examid": "否",
                "scr_examfn": "是",
                "scr_exambf": "否",
                "cls_name": "金融專班碩一",
                "scr_period": "(日)06-08 商1009 呂瑞秋",
                "scr_precnt": 25.0,
                "scr_acptcnt": 22.0,
                "scr_remarks": null,
                "unt_ls": 4804,
                "cls_id": "CF0131A",
                "sub_id": "22910",
                "scr_dup": "001"
            },
            {
                "scr_selcode": "2229",
                "sub_id3": "INSU652",
                "sub_name": "保險法專題研究",
                "scr_credit": 3.0,
                "scj_scr_mso": "選修",
                "scr_examid": "否",
                "scr_examfn": "是",
                "scr_exambf": "否",
                "cls_name": "金融專班碩一",
                "scr_period": "(六)10-12 商1009 陳森松,郭德進",
                "scr_precnt": 20.0,
                "scr_acptcnt": 5.0,
                "scr_remarks": null,
                "unt_ls": 4804,
                "cls_id": "CF0131A",
                "sub_id": "28860",
                "scr_dup": "001"
            },
            {
                "scr_selcode": "2230",
                "sub_id3": "INSU678",
                "sub_name": "財產保險專題",
                "scr_credit": 3.0,
                "scj_scr_mso": "選修",
                "scr_examid": "否",
                "scr_examfn": "是",
                "scr_exambf": "否",
                "cls_name": "金融專班碩一",
                "scr_period": "(六)06-08 商1009 吳瑞雲",
                "scr_precnt": 20.0,
                "scr_acptcnt": 18.0,
                "scr_remarks": null,
                "unt_ls": 4804,
                "cls_id": "CF0131A",
                "sub_id": "38035",
                "scr_dup": "001"
            },
            {
                "scr_selcode": "2231",
                "sub_id3": "COF601",
                "sub_name": "研究方法",
                "scr_credit": 2.0,
                "scj_scr_mso": "必修",
                "scr_examid": "是",
                "scr_examfn": "是",
                "scr_exambf": "否",
                "cls_name": "金融專班碩二",
                "scr_period": "(六)03-04 商406 洪介偉",
                "scr_precnt": 40.0,
                "scr_acptcnt": 24.0,
                "scr_remarks": " ",
                "unt_ls": 4804,
                "cls_id": "CF0132A",
                "sub_id": "26210",
                "scr_dup": "001"
            },
            {
                "scr_selcode": "2232",
                "sub_id3": "COB601",
                "sub_name": "碩士論文",
                "scr_credit": 0.0,
                "scj_scr_mso": "必修",
                "scr_examid": "否",
                "scr_examfn": "否",
                "scr_exambf": "否",
                "cls_name": "金融專班碩二",
                "scr_period": " ",
                "scr_precnt": 40.0,
                "scr_acptcnt": 26.0,
                "scr_remarks": " ",
                "unt_ls": 4804,
                "cls_id": "CF0132A",
                "sub_id": "61530",
                "scr_dup": "001"
            },
            {
                "scr_selcode": "2233",
                "sub_id3": "INSU628",
                "sub_name": "人壽保險專題",
                "scr_credit": 3.0,
                "scj_scr_mso": "選修",
                "scr_examid": "否",
                "scr_examfn": "是",
                "scr_exambf": "否",
                "cls_name": "金融專班碩二",
                "scr_period": "(六)06-08 商1007 許文彥",
                "scr_precnt": 20.0,
                "scr_acptcnt": 8.0,
                "scr_remarks": null,
                "unt_ls": 4804,
                "cls_id": "CF0132A",
                "sub_id": "00041",
                "scr_dup": "001"
            },
            {
                "scr_selcode": "2234",
                "sub_id3": "INSU673",
                "sub_name": "大陸金融保險市場研究",
                "scr_credit": 3.0,
                "scj_scr_mso": "選修",
                "scr_examid": "否",
                "scr_examfn": "否",
                "scr_exambf": "否",
                "cls_name": "金融專班碩二",
                "scr_period": "(日)10-12 商1009 許文彥,董澍琦",
                "scr_precnt": 20.0,
                "scr_acptcnt": 11.0,
                "scr_remarks": null,
                "unt_ls": 4804,
                "cls_id": "CF0132A",
                "sub_id": "04391",
                "scr_dup": "001"
            },
            {
                "scr_selcode": "2235",
                "sub_id3": "FINA620",
                "sub_name": "衍生性金融商品",
                "scr_credit": 3.0,
                "scj_scr_mso": "選修",
                "scr_examid": "否",
                "scr_examfn": "是",
                "scr_exambf": "否",
                "cls_name": "金融專班碩二",
                "scr_period": "(三)12-14 商1009 許溪南",
                "scr_precnt": 25.0,
                "scr_acptcnt": 8.0,
                "scr_remarks": null,
                "unt_ls": 4804,
                "cls_id": "CF0132A",
                "sub_id": "30380",
                "scr_dup": "001"
            }
        ]
    }
}