{
    "d": {
        "message": "",
        "total": 31,
        "items": [
            {
                "scr_selcode": "0279",
                "sub_id3": "FINA600",
                "sub_name": "金融機構經營與管理",
                "scr_credit": 3.0,
                "scj_scr_mso": "必修",
                "scr_examid": "否",
                "scr_examfn": "否",
                "scr_exambf": "否",
                "cls_name": "財金碩一",
                "scr_period": "(三)02-04 商1215 李君屏",
                "scr_precnt": 20.0,
                "scr_acptcnt": 16.0,
                "scr_remarks": " ",
                "unt_ls": 4801,
                "cls_id": "CB03310",
                "sub_id": "22910",
                "scr_dup": "001"
            },
            {
                "scr_selcode": "0280",
                "sub_id3": "FINA620",
                "sub_name": "衍生性金融商品",
                "scr_credit": 3.0,
                "scj_scr_mso": "必修",
                "scr_examid": "否",
                "scr_examfn": "否",
                "scr_exambf": "否",
                "cls_name": "財金碩一",
                "scr_period": "(二)08-10 商1215 楊明晶",
                "scr_precnt": 20.0,
                "scr_acptcnt": 17.0,
                "scr_remarks": " ",
                "unt_ls": 4801,
                "cls_id": "CB03310",
                "sub_id": "30380",
                "scr_dup": "001"
            },
            {
                "scr_selcode": "0281",
                "sub_id3": "FINA633",
                "sub_name": "國際財務管理",
                "scr_credit": 3.0,
                "scj_scr_mso": "必修",
                "scr_examid": "否",
                "scr_examfn": "否",
                "scr_exambf": "否",
                "cls_name": "財金碩一",
                "scr_period": "(二)02-04 商1215 朱心蘅",
                "scr_precnt": 20.0,
                "scr_acptcnt": 20.0,
                "scr_remarks": " ",
                "unt_ls": 4801,
                "cls_id": "CB03310",
                "sub_id": "41890",
                "scr_dup": "001"
            },
            {
                "scr_selcode": "0282",
                "sub_id3": "FINA696",
                "sub_name": "論文研討(二)",
                "scr_credit": 1.0,
                "scj_scr_mso": "必修",
                "scr_examid": "否",
                "scr_examfn": "否",
                "scr_exambf": "否",
                "cls_name": "財金碩一",
                "scr_period": "(四)07     商512 陳清和",
                "scr_precnt": 30.0,
                "scr_acptcnt": 15.0,
                "scr_remarks": " ",
                "unt_ls": 4801,
                "cls_id": "CB03310",
                "sub_id": "68802",
                "scr_dup": "001"
            },
            {
                "scr_selcode": "0284",
                "sub_id3": "ECON632",
                "sub_name": "計量經濟學(二)",
                "scr_credit": 3.0,
                "scj_scr_mso": "選修",
                "scr_examid": "否",
                "scr_examfn": "否",
                "scr_exambf": "否",
                "cls_name": "財金碩一",
                "scr_period": "(二)11-13 商1215 劉炳麟",
                "scr_precnt": 25.0,
                "scr_acptcnt": 26.0,
                "scr_remarks": null,
                "unt_ls": 4801,
                "cls_id": "CB03310",
                "sub_id": "28320",
                "scr_dup": "001"
            },
            {
                "scr_selcode": "0285",
                "sub_id3": "FINA627",
                "sub_name": "期貨與選擇權理論與實務",
                "scr_credit": 3.0,
                "scj_scr_mso": "選修",
                "scr_examid": "否",
                "scr_examfn": "否",
                "scr_exambf": "否",
                "cls_name": "財金碩一",
                "scr_period": "(一)02-04 商1215 吳仰哲",
                "scr_precnt": 20.0,
                "scr_acptcnt": 16.0,
                "scr_remarks": null,
                "unt_ls": 4801,
                "cls_id": "CB03310",
                "sub_id": "48311",
                "scr_dup": "001"
            },
            {
                "scr_selcode": "0286",
                "sub_id3": "COB601",
                "sub_name": "碩士論文",
                "scr_credit": 0.0,
                "scj_scr_mso": "必修",
                "scr_examid": "否",
                "scr_examfn": "否",
                "scr_exambf": "否",
                "cls_name": "財金碩二",
                "scr_period": "(六)00     未排教室",
                "scr_precnt": 30.0,
                "scr_acptcnt": 21.0,
                "scr_remarks": " ",
                "unt_ls": 4801,
                "cls_id": "CB03320",
                "sub_id": "61530",
                "scr_dup": "001"
            },
            {
                "scr_selcode": "0287",
                "sub_id3": "FINA653",
                "sub_name": "投資策略",
                "scr_credit": 3.0,
                "scj_scr_mso": "選修",
                "scr_examid": "否",
                "scr_examfn": "否",
                "scr_exambf": "否",
                "cls_name": "財金碩二",
                "scr_period": "(三)06-08 商1215 簡正儀",
                "scr_precnt": 20.0,
                "scr_acptcnt": 12.0,
                "scr_remarks": null,
                "unt_ls": 4801,
                "cls_id": "CB03320",
                "sub_id": "18691",
                "scr_dup": "001"
            },
            {
                "scr_selcode": "0340",
                "sub_id3": "INSU602",
                "sub_name": "保險法",
                "scr_credit": 3.0,
                "scj_scr_mso": "必修",
                "scr_examid": "否",
                "scr_examfn": "否",
                "scr_exambf": "否",
                "cls_name": "風管與保險碩一",
                "scr_period": "(二)02-04 商1007 陳森松",
                "scr_precnt": 25.0,
                "scr_acptcnt": 16.0,
                "scr_remarks": " ",
                "unt_ls": 4802,
                "cls_id": "CB04310",
                "sub_id": "28850",
                "scr_dup": "001"
            },
            {
                "scr_selcode": "0341",
                "sub_id3": "INSU604",
                "sub_name": "風險管理與保險",
                "scr_credit": 3.0,
                "scj_scr_mso": "必修",
                "scr_examid": "否",
                "scr_examfn": "否",
                "scr_exambf": "否",
                "cls_name": "風管與保險碩一",
                "scr_period": "(一)07-09 商1007 許文彥",
                "scr_precnt": 25.0,
                "scr_acptcnt": 17.0,
                "scr_remarks": " ",
                "unt_ls": 4802,
                "cls_id": "CB04310",
                "sub_id": "30562",
                "scr_dup": "001"
            },
            {
                "scr_selcode": "0342",
                "sub_id3": "FINA636",
                "sub_name": "財務專題(二)",
                "scr_credit": 3.0,
                "scj_scr_mso": "必修",
                "scr_examid": "否",
                "scr_examfn": "否",
                "scr_exambf": "否",
                "cls_name": "風管與保險碩一",
                "scr_period": "(五)07-09 商1009 張智凱,詹志清",
                "scr_precnt": 20.0,
                "scr_acptcnt": 12.0,
                "scr_remarks": " ",
                "unt_ls": 4802,
                "cls_id": "CB04310",
                "sub_id": "37887",
                "scr_dup": "001"
            },
            {
                "scr_selcode": "0343",
                "sub_id3": "INSU628",
                "sub_name": "人壽保險專題",
                "scr_credit": 3.0,
                "scj_scr_mso": "選修",
                "scr_examid": "否",
                "scr_examfn": "否",
                "scr_exambf": "否",
                "cls_name": "風管與保險碩一",
                "scr_period": "(三)02-04 商1009 黃雅文",
                "scr_precnt": 20.0,
                "scr_acptcnt": 6.0,
                "scr_remarks": null,
                "unt_ls": 4802,
                "cls_id": "CB04310",
                "sub_id": "00041",
                "scr_dup": "001"
            },
            {
                "scr_selcode": "0344",
                "sub_id3": "INSU638",
                "sub_name": "企業風險管理",
                "scr_credit": 3.0,
                "scj_scr_mso": "選修",
                "scr_examid": "否",
                "scr_examfn": "否",
                "scr_exambf": "否",
                "cls_name": "風管與保險碩一",
                "scr_period": "(五)02-04 商1009 張永郎",
                "scr_precnt": 20.0,
                "scr_acptcnt": 3.0,
                "scr_remarks": null,
                "unt_ls": 4802,
                "cls_id": "CB04310",
                "sub_id": "15870",
                "scr_dup": "001"
            },
            {
                "scr_selcode": "0345",
                "sub_id3": "INSU711",
                "sub_name": "保險會計與財務分析",
                "scr_credit": 3.0,
                "scj_scr_mso": "選修",
                "scr_examid": "否",
                "scr_examfn": "否",
                "scr_exambf": "否",
                "cls_name": "風管與保險碩一",
                "scr_period": "(四)07-09 商1009 鄒政下",
                "scr_precnt": 20.0,
                "scr_acptcnt": 9.0,
                "scr_remarks": null,
                "unt_ls": 4802,
                "cls_id": "CB04310",
                "sub_id": "28905",
                "scr_dup": "001"
            },
            {
                "scr_selcode": "0346",
                "sub_id3": "INSU656",
                "sub_name": "財產保險研究(一)",
                "scr_credit": 3.0,
                "scj_scr_mso": "選修",
                "scr_examid": "否",
                "scr_examfn": "否",
                "scr_exambf": "否",
                "cls_name": "風管與保險碩一",
                "scr_period": "(三)07-09 商1009 吳瑞雲",
                "scr_precnt": 20.0,
                "scr_acptcnt": 5.0,
                "scr_remarks": null,
                "unt_ls": 4802,
                "cls_id": "CB04310",
                "sub_id": "38071",
                "scr_dup": "001"
            },
            {
                "scr_selcode": "0347",
                "sub_id3": "STAT628",
                "sub_name": "數量方法(一)",
                "scr_credit": 3.0,
                "scj_scr_mso": "選修",
                "scr_examid": "否",
                "scr_examfn": "否",
                "scr_exambf": "否",
                "cls_name": "風管與保險碩一",
                "scr_period": "(二)11-13 商1009 洪介偉",
                "scr_precnt": 25.0,
                "scr_acptcnt": 20.0,
                "scr_remarks": null,
                "unt_ls": 4802,
                "cls_id": "CB04310",
                "sub_id": "62570",
                "scr_dup": "001"
            },
            {
                "scr_selcode": "4428",
                "sub_id3": "INSU622",
                "sub_name": "人壽及健康保險",
                "scr_credit": 3.0,
                "scj_scr_mso": "選修",
                "scr_examid": "是",
                "scr_examfn": "是",
                "scr_exambf": "否",
                "cls_name": "風管與保險碩一",
                "scr_period": "(二)07-09 商1009 宮可倫",
                "scr_precnt": 60.0,
                "scr_acptcnt": 16.0,
                "scr_remarks": null,
                "unt_ls": 4802,
                "cls_id": "CB04310",
                "sub_id": "00050",
                "scr_dup": "001"
            },
            {
                "scr_selcode": "0348",
                "sub_id3": "INSU692",
                "sub_name": "專題討論(二)",
                "scr_credit": 1.0,
                "scj_scr_mso": "必修",
                "scr_examid": "否",
                "scr_examfn": "否",
                "scr_exambf": "否",
                "cls_name": "風管與保險碩二",
                "scr_period": "(六)01     商1007 洪介偉",
                "scr_precnt": 20.0,
                "scr_acptcnt": 16.0,
                "scr_remarks": " ",
                "unt_ls": 4802,
                "cls_id": "CB04320",
                "sub_id": "43140",
                "scr_dup": "001"
            },
            {
                "scr_selcode": "0349",
                "sub_id3": "COB601",
                "sub_name": "碩士論文",
                "scr_credit": 0.0,
                "scj_scr_mso": "必修",
                "scr_examid": "是",
                "scr_examfn": "是",
                "scr_exambf": "否",
                "cls_name": "風管與保險碩二",
                "scr_period": "(日)00     未排教室",
                "scr_precnt": 60.0,
                "scr_acptcnt": 16.0,
                "scr_remarks": " ",
                "unt_ls": 4802,
                "cls_id": "CB04320",
                "sub_id": "61530",
                "scr_dup": "001"
            },
            {
                "scr_selcode": "0351",
                "sub_id3": "INSU648",
                "sub_name": "保險產業專業實習",
                "scr_credit": 6.0,
                "scj_scr_mso": "選修",
                "scr_examid": "否",
                "scr_examfn": "否",
                "scr_exambf": "否",
                "cls_name": "風管與保險碩二",
                "scr_period": "(五)00     未排教室 (日)01     未排教室 許文彥,黃雅文,吳瑞雲,曾鹿鳴",
                "scr_precnt": 20.0,
                "scr_acptcnt": 2.0,
                "scr_remarks": "此課程配合風保系「3+1實習計畫開設」。  不開放線上加選",
                "unt_ls": 4802,
                "cls_id": "CB04320",
                "sub_id": "28553",
                "scr_dup": "001"
            },
            {
                "scr_selcode": "0352",
                "sub_id3": "INSU647",
                "sub_name": "保險財務專題",
                "scr_credit": 3.0,
                "scj_scr_mso": "選修",
                "scr_examid": "否",
                "scr_examfn": "否",
                "scr_exambf": "否",
                "cls_name": "風管與保險碩二",
                "scr_period": "(二)02-04 商1009 張智凱",
                "scr_precnt": 20.0,
                "scr_acptcnt": 11.0,
                "scr_remarks": null,
                "unt_ls": 4802,
                "cls_id": "CB04320",
                "sub_id": "29053",
                "scr_dup": "001"
            },
            {
                "scr_selcode": "0353",
                "sub_id3": "INSU634",
                "sub_name": "政策保險專題研究",
                "scr_credit": 3.0,
                "scj_scr_mso": "選修",
                "scr_examid": "否",
                "scr_examfn": "否",
                "scr_exambf": "否",
                "cls_name": "風管與保險碩二",
                "scr_period": "(二)07-09 商1007 簡宣博",
                "scr_precnt": 20.0,
                "scr_acptcnt": 9.0,
                "scr_remarks": null,
                "unt_ls": 4802,
                "cls_id": "CB04320",
                "sub_id": "29212",
                "scr_dup": "001"
            },
            {
                "scr_selcode": "2030",
                "sub_id3": "FINA662",
                "sub_name": "投資學",
                "scr_credit": 3.0,
                "scj_scr_mso": "必修",
                "scr_examid": "是",
                "scr_examfn": "是",
                "scr_exambf": "否",
                "cls_name": "金融專班碩一",
                "scr_period": "(六)02-04 商403 簡正儀",
                "scr_precnt": 35.0,
                "scr_acptcnt": 24.0,
                "scr_remarks": " ",
                "unt_ls": 4804,
                "cls_id": "CF0131A",
                "sub_id": "18700",
                "scr_dup": "001"
            },
            {
                "scr_selcode": "2031",
                "sub_id3": "INSU671",
                "sub_name": "保險學",
                "scr_credit": 3.0,
                "scj_scr_mso": "必修",
                "scr_examid": "是",
                "scr_examfn": "是",
                "scr_exambf": "否",
                "cls_name": "金融專班碩一",
                "scr_period": "(日)02-04 商403 許文彥",
                "scr_precnt": 35.0,
                "scr_acptcnt": 25.0,
                "scr_remarks": " ",
                "unt_ls": 4804,
                "cls_id": "CF0131A",
                "sub_id": "28800",
                "scr_dup": "001"
            },
            {
                "scr_selcode": "2032",
                "sub_id3": "INSU694",
                "sub_name": "人壽保險業務經營",
                "scr_credit": 3.0,
                "scj_scr_mso": "選修",
                "scr_examid": "否",
                "scr_examfn": "是",
                "scr_exambf": "否",
                "cls_name": "金融專班碩一",
                "scr_period": "(六)00     未排教室 (六)06-08 商1007 靳芸芬,鄭濟世",
                "scr_precnt": 25.0,
                "scr_acptcnt": 21.0,
                "scr_remarks": null,
                "unt_ls": 4804,
                "cls_id": "CF0131A",
                "sub_id": "00012",
                "scr_dup": "001"
            },
            {
                "scr_selcode": "2033",
                "sub_id3": "FINA679",
                "sub_name": "財務計量經濟學",
                "scr_credit": 3.0,
                "scj_scr_mso": "選修",
                "scr_examid": "是",
                "scr_examfn": "是",
                "scr_exambf": "否",
                "cls_name": "金融專班碩一",
                "scr_period": "(五)12-14 商1009 王佳真",
                "scr_precnt": 20.0,
                "scr_acptcnt": 6.0,
                "scr_remarks": null,
                "unt_ls": 4804,
                "cls_id": "CF0131A",
                "sub_id": "37351",
                "scr_dup": "001"
            },
            {
                "scr_selcode": "2034",
                "sub_id3": "ACCT625",
                "sub_name": "財務報表分析",
                "scr_credit": 3.0,
                "scj_scr_mso": "選修",
                "scr_examid": "是",
                "scr_examfn": "是",
                "scr_exambf": "否",
                "cls_name": "金融專班碩一",
                "scr_period": "(一)12-14 商1009 江耕南",
                "scr_precnt": 20.0,
                "scr_acptcnt": 5.0,
                "scr_remarks": null,
                "unt_ls": 4804,
                "cls_id": "CF0131A",
                "sub_id": "37910",
                "scr_dup": "001"
            },
            {
                "scr_selcode": "2035",
                "sub_id3": "COB601",
                "sub_name": "碩士論文",
                "scr_credit": 0.0,
                "scj_scr_mso": "必修",
                "scr_examid": "否",
                "scr_examfn": "否",
                "scr_exambf": "否",
                "cls_name": "金融專班碩二",
                "scr_period": "(日)00     未排教室",
                "scr_precnt": 30.0,
                "scr_acptcnt": 26.0,
                "scr_remarks": " ",
                "unt_ls": 4804,
                "cls_id": "CF0132A",
                "sub_id": "61530",
                "scr_dup": "001"
            },
            {
                "scr_selcode": "2036",
                "sub_id3": "COF602",
                "sub_name": "論文寫作",
                "scr_credit": 1.0,
                "scj_scr_mso": "必修",
                "scr_examid": "否",
                "scr_examfn": "是",
                "scr_exambf": "否",
                "cls_name": "金融專班碩二",
                "scr_period": "(六)04     商404 許文彥",
                "scr_precnt": 30.0,
                "scr_acptcnt": 24.0,
                "scr_remarks": " ",
                "unt_ls": 4804,
                "cls_id": "CF0132A",
                "sub_id": "68803",
                "scr_dup": "001"
            },
            {
                "scr_selcode": "2037",
                "sub_id3": "INSU617",
                "sub_name": "財產保險業務經營",
                "scr_credit": 3.0,
                "scj_scr_mso": "選修",
                "scr_examid": "是",
                "scr_examfn": "是",
                "scr_exambf": "否",
                "cls_name": "金融專班碩二",
                "scr_period": "(六)10-12 商1009 呂廣盛",
                "scr_precnt": 20.0,
                "scr_acptcnt": 15.0,
                "scr_remarks": null,
                "unt_ls": 4804,
                "cls_id": "CF0132A",
                "sub_id": "37352",
                "scr_dup": "001"
            },
            {
                "scr_selcode": "2038",
                "sub_id3": "ECON724",
                "sub_name": "國際金融理論",
                "scr_credit": 3.0,
                "scj_scr_mso": "選修",
                "scr_examid": "是",
                "scr_examfn": "是",
                "scr_exambf": "否",
                "cls_name": "金融專班碩二",
                "scr_period": "(四)12-14 商1009 洪偉峰",
                "scr_precnt": 20.0,
                "scr_acptcnt": 10.0,
                "scr_remarks": null,
                "unt_ls": 4804,
                "cls_id": "CF0132A",
                "sub_id": "41461",
                "scr_dup": "001"
            }
        ]
    }
}